<?xml version="1.0" encoding="UTF-8"?>
<MetaDataObject xmlns="http://v8.1c.ru/8.3/MDClasses" xmlns:app="http://v8.1c.ru/8.2/managed-application/core" xmlns:cfg="http://v8.1c.ru/8.1/data/enterprise/current-config" xmlns:cmi="http://v8.1c.ru/8.2/managed-application/cmi" xmlns:ent="http://v8.1c.ru/8.1/data/enterprise" xmlns:lf="http://v8.1c.ru/8.2/managed-application/logform" xmlns:style="http://v8.1c.ru/8.1/data/ui/style" xmlns:sys="http://v8.1c.ru/8.1/data/ui/fonts/system" xmlns:v8="http://v8.1c.ru/8.1/data/core" xmlns:v8ui="http://v8.1c.ru/8.1/data/ui" xmlns:web="http://v8.1c.ru/8.1/data/ui/colors/web" xmlns:win="http://v8.1c.ru/8.1/data/ui/colors/windows" xmlns:xen="http://v8.1c.ru/8.3/xcf/enums" xmlns:xpr="http://v8.1c.ru/8.3/xcf/predef" xmlns:xr="http://v8.1c.ru/8.3/xcf/readable" xmlns:xs="http://www.w3.org/2001/XMLSchema" xmlns:xsi="http://www.w3.org/2001/XMLSchema-instance" version="2.18">
	<EventSubscription uuid="4a3ee90b-602a-4f18-a439-fa53fd7b2fb9">
		<Properties>
			<Name>АвтономнаяРаботаРегистрацияУдаления</Name>
			<Synonym>
				<v8:item>
					<v8:lang>ru</v8:lang>
					<v8:content>Автономная работа регистрация удаления</v8:content>
				</v8:item>
			</Synonym>
			<Comment/>
			<Source>
				<v8:Type>cfg:DocumentObject.РешениеОПриемеНаРаботу</v8:Type>
				<v8:Type>cfg:CatalogObject.СтраныМира</v8:Type>
				<v8:Type>cfg:DocumentObject.ДанныеОКорректировкеСведенийЗастрахованныхЛицСЗВ_КОРР</v8:Type>
				<v8:Type>cfg:CatalogObject.СправкиФизическихЛицПрисоединенныеФайлы</v8:Type>
				<v8:Type>cfg:DocumentObject.РеестрСведенийНеобходимыхДляНазначенияИВыплатыПособий</v8:Type>
				<v8:Type>cfg:CatalogObject.ВидыДоходовНДФЛ</v8:Type>
				<v8:Type>cfg:CatalogObject.СообщениеSMSПрисоединенныеФайлы</v8:Type>
				<v8:Type>cfg:CatalogObject.НазначениеПоказателейЭффективностиПрисоединенныеФайлы</v8:Type>
				<v8:Type>cfg:DocumentObject.СообщениеОНеправильныхДанныхСотрудника</v8:Type>
				<v8:Type>cfg:CatalogObject.ПерерасчетСтраховыхВзносовПрисоединенныеФайлы</v8:Type>
				<v8:Type>cfg:DocumentObject.ПрогулНеявкаСписком</v8:Type>
				<v8:Type>cfg:CatalogObject.РасширенияПрограммМедицинскогоСтрахования</v8:Type>
				<v8:Type>cfg:CatalogObject.ОтменаЗаявкиНаОтпускПрисоединенныеФайлы</v8:Type>
				<v8:Type>cfg:CatalogObject.ОснованияЗаключенияСрочныхТрудовыхДоговоров</v8:Type>
				<v8:Type>cfg:ChartOfCharacteristicTypesObject.ШтатноеРасписаниеПодключаемыеХарактеристики</v8:Type>
				<v8:Type>cfg:CatalogObject.СоставыВоеннослужащих</v8:Type>
				<v8:Type>cfg:CatalogObject.КодыДокументовКадровыхМероприятий</v8:Type>
				<v8:Type>cfg:CatalogObject.ОплатаПоСреднемуЗаработкуСпискомПрисоединенныеФайлы</v8:Type>
				<v8:Type>cfg:CatalogObject.НазначениеПодработкиПрисоединенныеФайлы</v8:Type>
				<v8:Type>cfg:CatalogObject.ОтменаДоплатыДоСреднегоЗаработкаПрисоединенныеФайлы</v8:Type>
				<v8:Type>cfg:CatalogObject.МестаРаботы</v8:Type>
				<v8:Type>cfg:CatalogObject.МакетыПечатныхФорм</v8:Type>
				<v8:Type>cfg:CatalogObject.ДанныеОКорректировкеСведенийЗастрахованныхЛицСЗВ_КОРРПрисоединенныеФайлы</v8:Type>
				<v8:Type>cfg:CatalogObject.ИсполнительныйЛистПрисоединенныеФайлы</v8:Type>
				<v8:Type>cfg:CatalogObject.ОрганизацииПрисоединенныеФайлы</v8:Type>
				<v8:Type>cfg:CatalogObject.КлассификаторБанков</v8:Type>
				<v8:Type>cfg:CatalogObject.БронированиеГражданПребывающихВЗапасеПрисоединенныеФайлы</v8:Type>
				<v8:Type>cfg:CatalogObject.СтатьиРасходовЗарплата</v8:Type>
				<v8:Type>cfg:DocumentObject.ПачкаРазделов6РасчетаРСВ_1</v8:Type>
				<v8:Type>cfg:CatalogObject.ПлатежноеПоручениеПрисоединенныеФайлы</v8:Type>
				<v8:Type>cfg:DocumentObject.СведенияОНезачисленнойЗарплате</v8:Type>
				<v8:Type>cfg:CatalogObject.РаспределениеОсновногоЗаработкаПрисоединенныеФайлы</v8:Type>
				<v8:Type>cfg:CatalogObject.ПереносОтпускаПрисоединенныеФайлы</v8:Type>
				<v8:Type>cfg:CatalogObject.ИзменениеЛьготСотрудниковПрисоединенныеФайлы</v8:Type>
				<v8:Type>cfg:CatalogObject.СправкиПоНДФЛДляРасчетаПоНалогуНаПрибыльПрисоединенныеФайлы</v8:Type>
				<v8:Type>cfg:CatalogObject.ИндексацияЗаработкаПрисоединенныеФайлы</v8:Type>
				<v8:Type>cfg:DocumentObject.УтверждениеТарифнойСетки</v8:Type>
				<v8:Type>cfg:DocumentObject.ИнструктажПоОхранеТруда</v8:Type>
				<v8:Type>cfg:CatalogObject.ПланПоказателейЭффективностиСотрудникаПрисоединенныеФайлы</v8:Type>
				<v8:Type>cfg:DocumentObject.ОписьПачекСЗВ_6</v8:Type>
				<v8:Type>cfg:CatalogObject.ВидыДокументовВводДанныхДляРасчетаЗарплаты</v8:Type>
				<v8:Type>cfg:DocumentObject.СправкаНДФЛ</v8:Type>
				<v8:Type>cfg:CatalogObject.КомплектыОтчетностиПерсУчета</v8:Type>
				<v8:Type>cfg:CatalogObject.СтатьиФинансированияЗарплата</v8:Type>
				<v8:Type>cfg:CatalogObject.УченическийДоговорПрисоединенныеФайлы</v8:Type>
				<v8:Type>cfg:ChartOfCharacteristicTypesObject.ВопросыДляАнкетирования</v8:Type>
				<v8:Type>cfg:DocumentObject.ПеремещениеВДругоеПодразделение</v8:Type>
				<v8:Type>cfg:CatalogObject.ПравилаИнтеграцииС1СДокументооборотом3</v8:Type>
				<v8:Type>cfg:CatalogObject.ШаблоныАнкет</v8:Type>
				<v8:Type>cfg:CatalogObject.ТеорияЭлектронныхКурсов</v8:Type>
				<v8:Type>cfg:CatalogObject.ПеремещениеВДругоеПодразделениеПрисоединенныеФайлы</v8:Type>
				<v8:Type>cfg:CatalogObject.ОплатаДнейУходаЗаДетьмиИнвалидамиПрисоединенныеФайлы</v8:Type>
				<v8:Type>cfg:CatalogObject.ОперацияНалоговогоУчетаПоНДФЛПрисоединенныеФайлы</v8:Type>
				<v8:Type>cfg:CatalogObject.ВидыАттестацийСотрудников</v8:Type>
				<v8:Type>cfg:CatalogObject.ПодтверждениеВыплатыДоходовПрисоединенныеФайлы</v8:Type>
				<v8:Type>cfg:CatalogObject.ПричиныОткрытияВакансий</v8:Type>
				<v8:Type>cfg:CatalogObject.ГруппыИсполнителейЗадач</v8:Type>
				<v8:Type>cfg:CatalogObject.ВидыИспользованияРабочегоВремени</v8:Type>
				<v8:Type>cfg:CatalogObject.УплатаСтраховыхВзносовВФондыПрисоединенныеФайлы</v8:Type>
				<v8:Type>cfg:CatalogObject.ОтражениеЗарплатыВФинансовомУчетеПрисоединенныеФайлы</v8:Type>
				<v8:Type>cfg:DocumentObject.ОтражениеУдержанногоНДФЛВБухучете</v8:Type>
				<v8:Type>cfg:CatalogObject.ФормыЗачетаМероприятийОбучения</v8:Type>
				<v8:Type>cfg:CatalogObject.ПостоянноеУдержаниеВПользуТретьихЛицПрисоединенныеФайлы</v8:Type>
				<v8:Type>cfg:DocumentObject.ОписьОДВ_1</v8:Type>
				<v8:Type>cfg:CatalogObject.СтепениЗнанияЯзыкаКандидата</v8:Type>
				<v8:Type>cfg:CatalogObject.НастройкиАвторизацииИнтернетСервисов</v8:Type>
				<v8:Type>cfg:CatalogObject.РеестрДСВ_3ПрисоединенныеФайлы</v8:Type>
				<v8:Type>cfg:CatalogObject.УдержаниеДобровольныхВзносовВНПФПрисоединенныеФайлы</v8:Type>
				<v8:Type>cfg:DocumentObject.ПереносОтпуска</v8:Type>
				<v8:Type>cfg:DocumentObject.ИндексацияЗаработка</v8:Type>
				<v8:Type>cfg:CatalogObject.ВерсииФайлов</v8:Type>
				<v8:Type>cfg:CatalogObject.ВедомостьПрочихДоходовВБанкПрисоединенныеФайлы</v8:Type>
				<v8:Type>cfg:CatalogObject.ЗарплатныеПроекты</v8:Type>
				<v8:Type>cfg:DocumentObject.АктОбУничтоженииПерсональныхДанных</v8:Type>
				<v8:Type>cfg:DocumentObject.ПерерасчетНДФЛ</v8:Type>
				<v8:Type>cfg:CatalogObject.ПоказателиКадровогоПланирования</v8:Type>
				<v8:Type>cfg:CatalogObject.УдержаниеПрофсоюзныхВзносовПрисоединенныеФайлы</v8:Type>
				<v8:Type>cfg:DocumentObject.ВосстановлениеВДолжности</v8:Type>
				<v8:Type>cfg:CatalogObject.РегистрацияПереработокПрисоединенныеФайлы</v8:Type>
				<v8:Type>cfg:DocumentObject.РазовоеНачисление</v8:Type>
				<v8:Type>cfg:CatalogObject.ФактПоказателяЭффективностиПодразделенийПрисоединенныеФайлы</v8:Type>
				<v8:Type>cfg:DocumentObject.ВыплатаБывшимСотрудникам</v8:Type>
				<v8:Type>cfg:CatalogObject.ПричиныОтклоненияКандидатов</v8:Type>
				<v8:Type>cfg:CatalogObject.ВидыУведомлений</v8:Type>
				<v8:Type>cfg:CatalogObject.ПапкиФайлов</v8:Type>
				<v8:Type>cfg:DocumentObject.ДоговорРаботыУслуги</v8:Type>
				<v8:Type>cfg:CatalogObject.КадровыйПланПрисоединенныеФайлы</v8:Type>
				<v8:Type>cfg:CatalogObject.РешениеОПриемеНаРаботуПрисоединенныеФайлы</v8:Type>
				<v8:Type>cfg:DocumentObject.РешениеОбОтпускеПоУходуЗаРебенком</v8:Type>
				<v8:Type>cfg:CatalogObject.ПачкаДокументовСПВ_1ПрисоединенныеФайлы</v8:Type>
				<v8:Type>cfg:CatalogObject.УдержаниеДобровольныхСтраховыхВзносовПрисоединенныеФайлы</v8:Type>
				<v8:Type>cfg:CatalogObject.ПачкаДокументовАДВ_2ПрисоединенныеФайлы</v8:Type>
				<v8:Type>cfg:CatalogObject.РазрядыКатегорииДолжностей</v8:Type>
				<v8:Type>cfg:CatalogObject.ВидыПроисшествий</v8:Type>
				<v8:Type>cfg:CatalogObject.УведомлениеОПравеНаИмущественныйВычетДляНДФЛПрисоединенныеФайлы</v8:Type>
				<v8:Type>cfg:CatalogObject.СверкаСДокументамиВоинскогоУчетаПрисоединенныеФайлы</v8:Type>
				<v8:Type>cfg:CatalogObject.ПрикреплениеКПрограммамМедицинскогоСтрахованияПрисоединенныеФайлы</v8:Type>
				<v8:Type>cfg:CatalogObject.ОсобыеУсловияТрудаДляСЗВКПФР</v8:Type>
				<v8:Type>cfg:CatalogObject.ПричиныПроисшествий</v8:Type>
				<v8:Type>cfg:CatalogObject.СтрокиОтчетностиМониторингаРаботниковСоциальнойСферы</v8:Type>
				<v8:Type>cfg:CatalogObject.ИзменениеОплатыТрудаПрисоединенныеФайлы</v8:Type>
				<v8:Type>cfg:CatalogObject.ЗапросСправкиСотрудникомПрисоединенныеФайлы</v8:Type>
				<v8:Type>cfg:CatalogObject.ЗаявкаНаОтпускПрисоединенныеФайлы</v8:Type>
				<v8:Type>cfg:CatalogObject.РаботаВВыходныеИПраздничныеДниПрисоединенныеФайлы</v8:Type>
				<v8:Type>cfg:CatalogObject.ДоговорРаботыУслугиПрисоединенныеФайлы</v8:Type>
				<v8:Type>cfg:CatalogObject.СпособыВыплатыЗарплаты</v8:Type>
				<v8:Type>cfg:DocumentObject.ПачкаДокументовСПВ_1</v8:Type>
				<v8:Type>cfg:CatalogObject.ЗапросВФССОПроверкеРаботодателяПрисоединенныеФайлы</v8:Type>
				<v8:Type>cfg:DocumentObject.РезультатыАттестацииСотрудников</v8:Type>
				<v8:Type>cfg:DocumentObject.ЗапросВФССОПроверкеРаботодателя</v8:Type>
				<v8:Type>cfg:CatalogObject.БухучетНачисленийСотрудниковПрисоединенныеФайлы</v8:Type>
				<v8:Type>cfg:ChartOfCharacteristicTypesObject.ОбъектыАдресацииЗадач</v8:Type>
				<v8:Type>cfg:DocumentObject.ОплатаДнейУходаЗаДетьмиИнвалидами</v8:Type>
				<v8:Type>cfg:CatalogObject.КлассификаторЗанятий</v8:Type>
				<v8:Type>cfg:CatalogObject.ВидыСтажа</v8:Type>
				<v8:Type>cfg:DocumentObject.УченическийДоговор</v8:Type>
				<v8:Type>cfg:CatalogObject.ПереводКДругомуРаботодателюПрисоединенныеФайлы</v8:Type>
				<v8:Type>cfg:CatalogObject.ПротоколОпросаУчастникаНесчастногоСлучаяПрисоединенныеФайлы</v8:Type>
				<v8:Type>cfg:DocumentObject.РаботаВВыходныеИПраздничныеДни</v8:Type>
				<v8:Type>cfg:CatalogObject.КадровыйРезерв</v8:Type>
				<v8:Type>cfg:CatalogObject.ИндивидуальныйГрафикПрисоединенныеФайлы</v8:Type>
				<v8:Type>cfg:CatalogObject.ШаблоныСообщений</v8:Type>
				<v8:Type>cfg:CatalogObject.ПачкаДокументовАДВ_3ПрисоединенныеФайлы</v8:Type>
				<v8:Type>cfg:CatalogObject.ФизическиеЛицаПрисоединенныеФайлы</v8:Type>
				<v8:Type>cfg:DocumentObject.НазначениеРабочихМестСотрудникам</v8:Type>
				<v8:Type>cfg:CatalogObject.ГруппыДоступаКандидатов</v8:Type>
				<v8:Type>cfg:CatalogObject.СведенияОТрудовойДеятельностиРаботниковСЗВ_ТДПрисоединенныеФайлы</v8:Type>
				<v8:Type>cfg:CatalogObject.НачислениеЗарплатыПрисоединенныеФайлы</v8:Type>
				<v8:Type>cfg:DocumentObject.ОтменаЗаявкиНаКомандировку</v8:Type>
				<v8:Type>cfg:DocumentObject.ПачкаДокументовДСВ_1</v8:Type>
				<v8:Type>cfg:CatalogObject.ПланПоказателяЭффективностиПозицийПрисоединенныеФайлы</v8:Type>
				<v8:Type>cfg:DocumentObject.ЛистокСообщенияДляВоенкомата</v8:Type>
				<v8:Type>cfg:DocumentObject.ПриказОбАттестацииСотрудников</v8:Type>
				<v8:Type>cfg:CatalogObject.ЗаявлениеОПодтвержденииПраваНаЗачетАвансовПоНДФЛПрисоединенныеФайлы</v8:Type>
				<v8:Type>cfg:DocumentObject.РеестрДанныхЭЛНЗаполняемыхРаботодателем</v8:Type>
				<v8:Type>cfg:DocumentObject.ПроизвольныйКадровыйПриказ</v8:Type>
				<v8:Type>cfg:DocumentObject.НазначениеПлановогоНачисления</v8:Type>
				<v8:Type>cfg:DocumentObject.РаспределениеОсновногоЗаработка</v8:Type>
				<v8:Type>cfg:CatalogObject.Демотиваторы</v8:Type>
				<v8:Type>cfg:CatalogObject.ЭлементыКлассификаторовМедРегистра</v8:Type>
				<v8:Type>cfg:CatalogObject.ПрогулНеявкаСпискомПрисоединенныеФайлы</v8:Type>
				<v8:Type>cfg:CatalogObject.ПростойСотрудниковПрисоединенныеФайлы</v8:Type>
				<v8:Type>cfg:CatalogObject.СостояниеВБраке</v8:Type>
				<v8:Type>cfg:CatalogObject.ЭлектронныеКурсы</v8:Type>
				<v8:Type>cfg:DocumentObject.ПеремещениеМеждуТерриториями</v8:Type>
				<v8:Type>cfg:DocumentObject.ПрекращениеПлановогоНачисления</v8:Type>
				<v8:Type>cfg:DocumentObject.ИзменениеШтатногоРасписания</v8:Type>
				<v8:Type>cfg:CatalogObject.ОбучениеРазвитиеСотрудниковПрисоединенныеФайлы</v8:Type>
				<v8:Type>cfg:CatalogObject.УчетныеЗаписиЭлектроннойПочты</v8:Type>
				<v8:Type>cfg:DocumentObject.ПогашениеЗаймаСотруднику</v8:Type>
				<v8:Type>cfg:CatalogObject.ФормированиеАттестационнойКомиссииСотрудниковПрисоединенныеФайлы</v8:Type>
				<v8:Type>cfg:CatalogObject.ВидыВыплатБывшимСотрудникам</v8:Type>
				<v8:Type>cfg:CatalogObject.РегистрацииВНалоговомОргане</v8:Type>
				<v8:Type>cfg:DocumentObject.ОтпускаСотрудников</v8:Type>
				<v8:Type>cfg:CatalogObject.ОтзывЗаявленийОПредоставленииСведенийОТрудовойДеятельностиПрисоединенныеФайлы</v8:Type>
				<v8:Type>cfg:CatalogObject.ОтражениеЗарплатыВБухучетеПрисоединенныеФайлы</v8:Type>
				<v8:Type>cfg:CatalogObject.ПогашениеЗаймаСотрудникуПрисоединенныеФайлы</v8:Type>
				<v8:Type>cfg:CatalogObject.ОтраслиНауки</v8:Type>
				<v8:Type>cfg:DocumentObject.БронированиеГражданПребывающихВЗапасе</v8:Type>
				<v8:Type>cfg:CatalogObject.ПриказНаДоплатуДоСреднегоЗаработкаПрисоединенныеФайлы</v8:Type>
				<v8:Type>cfg:CatalogObject.ПрофессииРабочих</v8:Type>
				<v8:Type>cfg:CatalogObject.ПрофилиДолжностейПрисоединенныеФайлы</v8:Type>
				<v8:Type>cfg:DocumentObject.ПодтверждениеВыплатыДоходов</v8:Type>
				<v8:Type>cfg:CatalogObject.ОтражениеРасходовНаПерсоналПрисоединенныеФайлы</v8:Type>
				<v8:Type>cfg:DocumentObject.ИсполнительныйЛист</v8:Type>
				<v8:Type>cfg:CatalogObject.НачальнаяЗадолженностьПоЗарплатеПрисоединенныеФайлы</v8:Type>
				<v8:Type>cfg:DocumentObject.ОтражениеЗарплатыВБухучете</v8:Type>
				<v8:Type>cfg:CatalogObject.НазначениеРабочихМестСотрудникамПрисоединенныеФайлы</v8:Type>
				<v8:Type>cfg:CatalogObject.ПоследствияНесчастногоСлучаяПрисоединенныеФайлы</v8:Type>
				<v8:Type>cfg:CatalogObject.ХодатайствоОБронированииГражданПребывающихВЗапасеПрисоединенныеФайлы</v8:Type>
				<v8:Type>cfg:CatalogObject.ИзменениеПлановыхНачисленийПрисоединенныеФайлы</v8:Type>
				<v8:Type>cfg:DocumentObject.ИзвещениеФСС</v8:Type>
				<v8:Type>cfg:CatalogObject.ГрафикиРаботыСотрудников</v8:Type>
				<v8:Type>cfg:CatalogObject.ПоказателиРасчетаЗарплаты</v8:Type>
				<v8:Type>cfg:DocumentObject.ПачкаДокументовСЗВ_6_1</v8:Type>
				<v8:Type>cfg:CatalogObject.ДоговорЗаймаСотрудникуПрисоединенныеФайлы</v8:Type>
				<v8:Type>cfg:DocumentObject.ПеречислениеНДФЛВБюджет</v8:Type>
				<v8:Type>cfg:DocumentObject.ЗаявкаНаПодборПерсонала</v8:Type>
				<v8:Type>cfg:CatalogObject.СправкиФизическихЛиц</v8:Type>
				<v8:Type>cfg:CatalogObject.ОтпускБезСохраненияОплатыСпискомПрисоединенныеФайлы</v8:Type>
				<v8:Type>cfg:CatalogObject.ОтпускаСотрудниковПрисоединенныеФайлы</v8:Type>
				<v8:Type>cfg:DocumentObject.ПачкаДокументовАДВ_3</v8:Type>
				<v8:Type>cfg:CatalogObject.ПериодыОплаченныеДоНачалаЭксплуатацииПрисоединенныеФайлы</v8:Type>
				<v8:Type>cfg:DocumentObject.ВозвратСотрудникомЗадолженности</v8:Type>
				<v8:Type>cfg:CatalogObject.ИзменениеГрафикаРаботыСпискомПрисоединенныеФайлы</v8:Type>
				<v8:Type>cfg:DocumentObject.ИндексацияШтатногоРасписания</v8:Type>
				<v8:Type>cfg:CatalogObject.ВидыМероприятияОбученияРазвития</v8:Type>
				<v8:Type>cfg:DocumentObject.ВозвратИзОтпускаПоУходуЗаРебенком</v8:Type>
				<v8:Type>cfg:DocumentObject.ОписьЗаявленийСотрудниковНаВыплатуПособий</v8:Type>
				<v8:Type>cfg:DocumentObject.ИзменениеКвалификационногоРазряда</v8:Type>
				<v8:Type>cfg:CatalogObject.ПереченьДолжностейДляБронированияГраждан</v8:Type>
				<v8:Type>cfg:CatalogObject.УсловияТруда</v8:Type>
				<v8:Type>cfg:CatalogObject.РешенияАттестационныхКомиссий</v8:Type>
				<v8:Type>cfg:DocumentObject.ИзменениеЛьготСотрудников</v8:Type>
				<v8:Type>cfg:DocumentObject.ПриостановлениеТрудовыхДоговоровКонтрактов</v8:Type>
				<v8:Type>cfg:DocumentObject.РаспределениеРасходовНаПерсонал</v8:Type>
				<v8:Type>cfg:CatalogObject.ИзвещениеФССПрисоединенныеФайлы</v8:Type>
				<v8:Type>cfg:DocumentObject.СведенияДляИсчисленияДоплатыКПенсииСЗВ_ДСО</v8:Type>
				<v8:Type>cfg:CatalogObject.УровниКомпетенцийПерсонала</v8:Type>
				<v8:Type>cfg:CatalogObject.ЭлементыЭлектронныхРесурсовПрисоединенныеФайлы</v8:Type>
				<v8:Type>cfg:CatalogObject.ЭлектронныеТесты</v8:Type>
				<v8:Type>cfg:DocumentObject.ЗапросСправкиСотрудником</v8:Type>
				<v8:Type>cfg:DocumentObject.ПереводКДругомуРаботодателю</v8:Type>
				<v8:Type>cfg:DocumentObject.СверкаСВоеннымКомиссариатом</v8:Type>
				<v8:Type>cfg:CatalogObject.ПризПодарокПрисоединенныеФайлы</v8:Type>
				<v8:Type>cfg:DocumentObject.ЗавершениеИспытательногоСрока</v8:Type>
				<v8:Type>cfg:CatalogObject.ПланПоказателяЭффективностиПодразделенийПрисоединенныеФайлы</v8:Type>
				<v8:Type>cfg:ChartOfCharacteristicTypesObject.СтатьиРасходов</v8:Type>
				<v8:Type>cfg:DocumentObject.ПубликацияМероприятияОбученияРазвития</v8:Type>
				<v8:Type>cfg:CatalogObject.СобеседникиЧатботов</v8:Type>
				<v8:Type>cfg:CatalogObject.НесчастныйСлучайНаПроизводствеПрисоединенныеФайлы</v8:Type>
				<v8:Type>cfg:CatalogObject.УдержаниеВСчетРасчетовПоПрочимОперациямПрисоединенныеФайлы</v8:Type>
				<v8:Type>cfg:CatalogObject.ЗакладкиВзаимодействий</v8:Type>
				<v8:Type>cfg:CatalogObject.ПрекращениеПодработкиПрисоединенныеФайлы</v8:Type>
				<v8:Type>cfg:CatalogObject.ПереносДанныхПрисоединенныеФайлы</v8:Type>
				<v8:Type>cfg:CatalogObject.ВидыДоходовПоСтраховымВзносам</v8:Type>
				<v8:Type>cfg:DocumentObject.УтверждениеШтатногоРасписания</v8:Type>
				<v8:Type>cfg:DocumentObject.ПодготовкаСпецоценкиУсловийТруда</v8:Type>
				<v8:Type>cfg:CatalogObject.ЭлементыЭлектронныхРесурсов</v8:Type>
				<v8:Type>cfg:DocumentObject.ПризПодарок</v8:Type>
				<v8:Type>cfg:DocumentObject.РаботаСверхурочно</v8:Type>
				<v8:Type>cfg:DocumentObject.ОплатаПоСреднемуЗаработку</v8:Type>
				<v8:Type>cfg:CatalogObject.ПрофилиГруппДоступа</v8:Type>
				<v8:Type>cfg:CatalogObject.ПрочиеРасходы</v8:Type>
				<v8:Type>cfg:CatalogObject.СогласиеНаУведомлениеОбЭЛНПрисоединенныеФайлы</v8:Type>
				<v8:Type>cfg:DocumentObject.Премия</v8:Type>
				<v8:Type>cfg:CatalogObject.ВидыОтправляемыхДокументов</v8:Type>
				<v8:Type>cfg:ChartOfCharacteristicTypesObject.РеквизитыПроизвольныхКадровыхПриказов</v8:Type>
				<v8:Type>cfg:CatalogObject.СтроковыеКонтактыВзаимодействий</v8:Type>
				<v8:Type>cfg:CatalogObject.ПрогулНеявкаПрисоединенныеФайлы</v8:Type>
				<v8:Type>cfg:DocumentObject.СреднийЗаработокСЭДО</v8:Type>
				<v8:Type>cfg:DocumentObject.НесчастныйСлучайНаПроизводстве</v8:Type>
				<v8:Type>cfg:CatalogObject.ИндивидуальныйПланРазвития</v8:Type>
				<v8:Type>cfg:DocumentObject.ПланПоказателяЭффективностиПозиций</v8:Type>
				<v8:Type>cfg:DocumentObject.ДанныеДляРасчетаЗарплаты</v8:Type>
				<v8:Type>cfg:CatalogObject.ПремияПрисоединенныеФайлы</v8:Type>
				<v8:Type>cfg:CatalogObject.ВстречаПрисоединенныеФайлы</v8:Type>
				<v8:Type>cfg:DocumentObject.УведомлениеОПрекращенииОтпускаПоУходуЗаРебенком</v8:Type>
				<v8:Type>cfg:CatalogObject.ПерерасчетНДФЛПрисоединенныеФайлы</v8:Type>
				<v8:Type>cfg:CatalogObject.ПачкаДокументовДСВ_1ПрисоединенныеФайлы</v8:Type>
				<v8:Type>cfg:CatalogObject.ОснованияИсчисляемогоСтраховогоСтажа</v8:Type>
				<v8:Type>cfg:CatalogObject.КатегорииПолучателейСтимулирующихВыплатФСС</v8:Type>
				<v8:Type>cfg:DocumentObject.ПрекращениеСтандартныхВычетовНДФЛ</v8:Type>
				<v8:Type>cfg:CatalogObject.СведенияДляФРМРПрисоединенныеФайлы</v8:Type>
				<v8:Type>cfg:CatalogObject.ОплатаПоСреднемуЗаработкуПрисоединенныеФайлы</v8:Type>
				<v8:Type>cfg:BusinessProcessObject.Задание</v8:Type>
				<v8:Type>cfg:CatalogObject.ДивидендыФизическимЛицамПрисоединенныеФайлы</v8:Type>
				<v8:Type>cfg:CatalogObject.УведомлениеОСпецрежимахНалогообложенияПрисоединенныеФайлы</v8:Type>
				<v8:Type>cfg:CatalogObject.ПереносЗатратНаПерсоналМеждуСтатьямиПрисоединенныеФайлы</v8:Type>
				<v8:Type>cfg:CatalogObject.ВидыПредоставляемыхСотрудникамСправок</v8:Type>
				<v8:Type>cfg:CatalogObject.РеестрСтимулирующихВыплатМедицинскимИСоциальнымРаботникамПрисоединенныеФайлы</v8:Type>
				<v8:Type>cfg:CatalogObject.СправкиНДФЛДляПередачиВНалоговыйОрганПрисоединенныеФайлы</v8:Type>
				<v8:Type>cfg:CatalogObject.СпособыОтраженияЗарплатыВБухУчете</v8:Type>
				<v8:Type>cfg:CatalogObject.ВидыИнструктажейПоОхранеТруда</v8:Type>
				<v8:Type>cfg:DocumentObject.ВозобновлениеТрудовыхДоговоровКонтрактов</v8:Type>
				<v8:Type>cfg:CatalogObject.ВыплатаБывшимСотрудникамПрисоединенныеФайлы</v8:Type>
				<v8:Type>cfg:DocumentObject.ВедомостьПрочихДоходовВКассу</v8:Type>
				<v8:Type>cfg:CatalogObject.ПачкаДокументовАДВ_1ПрисоединенныеФайлы</v8:Type>
				<v8:Type>cfg:CatalogObject.РежимыРаботыСотрудников</v8:Type>
				<v8:Type>cfg:DocumentObject.ПриемНаРаботуСписком</v8:Type>
				<v8:Type>cfg:DocumentObject.ЗаявкаНаОтпуск</v8:Type>
				<v8:Type>cfg:DocumentObject.НаправлениеНаВнешнююАттестацию</v8:Type>
				<v8:Type>cfg:CatalogObject.СтрокиОтчетностиРасходовИЧисленностиРаботниковГосударственныхОрганов</v8:Type>
				<v8:Type>cfg:CatalogObject.РешениеОбУвольненииПрисоединенныеФайлы</v8:Type>
				<v8:Type>cfg:CatalogObject.УвольнениеПрисоединенныеФайлы</v8:Type>
				<v8:Type>cfg:CatalogObject.ПачкаДокументовСЗВ_6_3ПрисоединенныеФайлы</v8:Type>
				<v8:Type>cfg:DocumentObject.АктПроверкиСтраховыхВзносов</v8:Type>
				<v8:Type>cfg:DocumentObject.ЗаявлениеВФССОВозмещенииРасходовНаПогребение</v8:Type>
				<v8:Type>cfg:CatalogObject.КомандировкаПрисоединенныеФайлы</v8:Type>
				<v8:Type>cfg:DocumentObject.НаправлениеНаМедицинскийОсмотр</v8:Type>
				<v8:Type>cfg:CatalogObject.ПубликацияМероприятияОбученияРазвитияПрисоединенныеФайлы</v8:Type>
				<v8:Type>cfg:DocumentObject.БухучетНачисленийСотрудников</v8:Type>
				<v8:Type>cfg:DocumentObject.РешениеОбУвольнении</v8:Type>
				<v8:Type>cfg:CatalogObject.Кандидаты</v8:Type>
				<v8:Type>cfg:CatalogObject.ВидыСправок</v8:Type>
				<v8:Type>cfg:DocumentObject.ИзучениеЭлектронногоКурса</v8:Type>
				<v8:Type>cfg:CatalogObject.ВидыКадровогоРезерва</v8:Type>
				<v8:Type>cfg:CatalogObject.ЗаявлениеСотрудникаНаВыплатуПособияПрисоединенныеФайлы</v8:Type>
				<v8:Type>cfg:CatalogObject.ЯзыкиПечатныхФорм</v8:Type>
				<v8:Type>cfg:CatalogObject.ПрекращениеСтандартныхВычетовНДФЛПрисоединенныеФайлы</v8:Type>
				<v8:Type>cfg:CatalogObject.РолиРеспондентаОценкиПерсонала</v8:Type>
				<v8:Type>cfg:CatalogObject.ОтпускБезСохраненияОплатыПрисоединенныеФайлы</v8:Type>
				<v8:Type>cfg:DocumentObject.ОграничениеВзысканий</v8:Type>
				<v8:Type>cfg:DocumentObject.НачальнаяШтатнаяРасстановка</v8:Type>
				<v8:Type>cfg:CatalogObject.АвансовыйПлатежИностранцаПоНДФЛПрисоединенныеФайлы</v8:Type>
				<v8:Type>cfg:CatalogObject.ШаблоныПроизвольныхКадровыхПриказов</v8:Type>
				<v8:Type>cfg:DocumentObject.ПродлениеИспытательногоСрока</v8:Type>
				<v8:Type>cfg:CatalogObject.ШаблоныВыплатПоДоговорамОпеки</v8:Type>
				<v8:Type>cfg:CatalogObject.ОписьПачекСЗВ_6ПрисоединенныеФайлы</v8:Type>
				<v8:Type>cfg:CatalogObject.ВходящийЗапросФССДляРасчетаПособияПрисоединенныеФайлы</v8:Type>
				<v8:Type>cfg:CatalogObject.ИзменениеУсловийОплатыОтпускаПоУходуЗаРебенкомПрисоединенныеФайлы</v8:Type>
				<v8:Type>cfg:CatalogObject.ВидыРаботСотрудников</v8:Type>
				<v8:Type>cfg:DocumentObject.ОперацияНалоговогоУчетаПоНДФЛ</v8:Type>
				<v8:Type>cfg:DocumentObject.УдержаниеДобровольныхСтраховыхВзносов</v8:Type>
				<v8:Type>cfg:CatalogObject.ЛичныеДанныеКандидатовПрисоединенныеФайлы</v8:Type>
				<v8:Type>cfg:DocumentObject.ОткреплениеОтПрограммМедицинскогоСтрахования</v8:Type>
				<v8:Type>cfg:DocumentObject.Встреча</v8:Type>
				<v8:Type>cfg:CatalogObject.ФактПоказателейЭффективностиПодразделенияПрисоединенныеФайлы</v8:Type>
				<v8:Type>cfg:CatalogObject.ПодготовкаСпецоценкиУсловийТрудаПрисоединенныеФайлы</v8:Type>
				<v8:Type>cfg:DocumentObject.КадровыйПеревод</v8:Type>
				<v8:Type>cfg:CatalogObject.РезервыПоОплатеТрудаПрисоединенныеФайлы</v8:Type>
				<v8:Type>cfg:CatalogObject.ВозвратСотрудникомЗадолженностиПрисоединенныеФайлы</v8:Type>
				<v8:Type>cfg:ChartOfCharacteristicTypesObject.НачисленияПодключаемыеХарактеристики</v8:Type>
				<v8:Type>cfg:CatalogObject.СтраницыЭлементовЭлектронныхКурсов</v8:Type>
				<v8:Type>cfg:CatalogObject.КандидатыПрисоединенныеФайлы</v8:Type>
				<v8:Type>cfg:CatalogObject.Проекты</v8:Type>
				<v8:Type>cfg:DocumentObject.ОтпускБезСохраненияОплаты</v8:Type>
				<v8:Type>cfg:DocumentObject.ИзменениеОплатыТруда</v8:Type>
				<v8:Type>cfg:CatalogObject.РеестрСЗВ_6_2ПрисоединенныеФайлы</v8:Type>
				<v8:Type>cfg:CatalogObject.ГруппыХарактеристикПерсонала</v8:Type>
				<v8:Type>cfg:CatalogObject.УченыеЗвания</v8:Type>
				<v8:Type>cfg:CatalogObject.РешениеОВозвратеИзОтпускаПоУходуЗаРебенкомПрисоединенныеФайлы</v8:Type>
				<v8:Type>cfg:DocumentObject.КомпенсацияЗаЗадержкуЗарплаты</v8:Type>
				<v8:Type>cfg:DocumentObject.УвольнениеСписком</v8:Type>
				<v8:Type>cfg:DocumentObject.НазначениеОпросов</v8:Type>
				<v8:Type>cfg:CatalogObject.ИзменениеУсловийМедицинскогоСтрахованияПрисоединенныеФайлы</v8:Type>
				<v8:Type>cfg:DocumentObject.РеестрСтимулирующихВыплатМедицинскимИСоциальнымРаботникам</v8:Type>
				<v8:Type>cfg:CatalogObject.ОснованияПриостановленияТрудовыхДоговоровКонтрактов</v8:Type>
				<v8:Type>cfg:CatalogObject.ОтменаБронированияГражданПребывающихВЗапасеПрисоединенныеФайлы</v8:Type>
				<v8:Type>cfg:CatalogObject.СпособыОкругленияПриРасчетеЗарплаты</v8:Type>
				<v8:Type>cfg:CatalogObject.ВредныеОпасныеПроизводственныеФакторыИВыполняемыеРаботы</v8:Type>
				<v8:Type>cfg:CatalogObject.НачислениеОценочныхОбязательствПоОтпускамПрисоединенныеФайлы</v8:Type>
				<v8:Type>cfg:DocumentObject.ОтменаЗаявкиНаОтпуск</v8:Type>
				<v8:Type>cfg:CatalogObject.ОбразованиеФизическихЛиц</v8:Type>
				<v8:Type>cfg:CatalogObject.ТелефонныйЗвонокПрисоединенныеФайлы</v8:Type>
				<v8:Type>cfg:CatalogObject.СведенияОТрудовойДеятельностиРаботникаСТД_РПрисоединенныеФайлы</v8:Type>
				<v8:Type>cfg:CatalogObject.ТерриторииСПовышающимКоэффициентомПоКоронавирусу</v8:Type>
				<v8:Type>cfg:CatalogObject.ЗавершениеИспытательногоСрокаПрисоединенныеФайлы</v8:Type>
				<v8:Type>cfg:CatalogObject.ТерриторииИПомещения</v8:Type>
				<v8:Type>cfg:CatalogObject.ВидыПрочихДоходовФизическихЛиц</v8:Type>
				<v8:Type>cfg:DocumentObject.СведенияОШтатномРасписанииДляМедРегистра</v8:Type>
				<v8:Type>cfg:DocumentObject.РезервыПоОплатеТруда</v8:Type>
				<v8:Type>cfg:CatalogObject.ТарифыПлатежныхАгентов</v8:Type>
				<v8:Type>cfg:CatalogObject.ЧатыЧатботов</v8:Type>
				<v8:Type>cfg:DocumentObject.ЗаявкаНаОбучениеРазвитие</v8:Type>
				<v8:Type>cfg:DocumentObject.ЗаявлениеВФССОВозмещенииВыплатРодителямДетейИнвалидов</v8:Type>
				<v8:Type>cfg:CatalogObject.МероприятияОценкиПерсонала</v8:Type>
				<v8:Type>cfg:CatalogObject.Кассы</v8:Type>
				<v8:Type>cfg:CatalogObject.ЗаявленияОПредоставленииСведенийОТрудовойДеятельностиПрисоединенныеФайлы</v8:Type>
				<v8:Type>cfg:CatalogObject.СамостоятельныеКлассификационныеЕдиницы</v8:Type>
				<v8:Type>cfg:CatalogObject.ПользовательскиеНастройкиОтчетов</v8:Type>
				<v8:Type>cfg:DocumentObject.ЗаключениеМедицинскогоОсмотра</v8:Type>
				<v8:Type>cfg:CatalogObject.ПачкаДокументовСЗВ_6_1ПрисоединенныеФайлы</v8:Type>
				<v8:Type>cfg:CatalogObject.УтверждениеШтатногоРасписанияПрисоединенныеФайлы</v8:Type>
				<v8:Type>cfg:DocumentObject.ВыгрузкаРегламентированныхОтчетов</v8:Type>
				<v8:Type>cfg:DocumentObject.ОбучениеРазвитиеСотрудников</v8:Type>
				<v8:Type>cfg:CatalogObject.ПрожиточныеМинимумы</v8:Type>
				<v8:Type>cfg:DocumentObject.ФормированиеАттестационнойКомиссииСотрудников</v8:Type>
				<v8:Type>cfg:CatalogObject.ПоказателиРасчетаРезервовПоОплатеТруда</v8:Type>
				<v8:Type>cfg:CatalogObject.СведенияОПриемеПереводеИУвольненииДляВоенкоматаПрисоединенныеФайлы</v8:Type>
				<v8:Type>cfg:DocumentObject.РешениеОВозвратеИзОтпускаПоУходуЗаРебенком</v8:Type>
				<v8:Type>cfg:DocumentObject.ТабельУчетаРабочегоВремени</v8:Type>
				<v8:Type>cfg:CatalogObject.ПереводНаРаботуСКоронавирусомПрисоединенныеФайлы</v8:Type>
				<v8:Type>cfg:CatalogObject.ЗаявкаНаПодборПерсоналаПрисоединенныеФайлы</v8:Type>
				<v8:Type>cfg:CatalogObject.МероприятияОбученияРазвития</v8:Type>
				<v8:Type>cfg:CatalogObject.ФизическиеЛица</v8:Type>
				<v8:Type>cfg:CatalogObject.НачислениеПоДоговорамПрисоединенныеФайлы</v8:Type>
				<v8:Type>cfg:DocumentObject.СведенияОРаботникахДляМедРегистра</v8:Type>
				<v8:Type>cfg:DocumentObject.НачальныеРасчетыСБюджетомПоНДФЛ</v8:Type>
				<v8:Type>cfg:CatalogObject.ЗаявлениеНаПредоставлениеСтандартныхВычетовПоНДФЛПрисоединенныеФайлы</v8:Type>
				<v8:Type>cfg:CatalogObject.ВидыТарифовСтраховыхВзносов</v8:Type>
				<v8:Type>cfg:CatalogObject.ИзменениеАвансаПрисоединенныеФайлы</v8:Type>
				<v8:Type>cfg:DocumentObject.ВедомостьНаВыплатуЗарплатыРаздатчиком</v8:Type>
				<v8:Type>cfg:CatalogObject.КлассификаторСпециальностейПоОбразованию</v8:Type>
				<v8:Type>cfg:CatalogObject.ПрекращениеПлановогоНачисленияПрисоединенныеФайлы</v8:Type>
				<v8:Type>cfg:CatalogObject.ГруппыДоступаФизическихЛиц</v8:Type>
				<v8:Type>cfg:CatalogObject.СпособыОтраженияВФинансовомУчете</v8:Type>
				<v8:Type>cfg:DocumentObject.ВедомостьНаВыплатуЗарплатыПеречислением</v8:Type>
				<v8:Type>cfg:CatalogObject.Должности</v8:Type>
				<v8:Type>cfg:CatalogObject.Организации</v8:Type>
				<v8:Type>cfg:CatalogObject.ЛистокСообщенияДляВоенкоматаПрисоединенныеФайлы</v8:Type>
				<v8:Type>cfg:CatalogObject.КадровыйПереводПрисоединенныеФайлы</v8:Type>
				<v8:Type>cfg:CatalogObject.ПозицииКадровогоПлана</v8:Type>
				<v8:Type>cfg:CatalogObject.СтепениЗнанияЯзыка</v8:Type>
				<v8:Type>cfg:CatalogObject.ВариантыОтветовНаТестовыеВопросы</v8:Type>
				<v8:Type>cfg:DocumentObject.ДивидендыФизическимЛицам</v8:Type>
				<v8:Type>cfg:DocumentObject.ИндивидуальныйГрафик</v8:Type>
				<v8:Type>cfg:DocumentObject.ГрафикОтпусков</v8:Type>
				<v8:Type>cfg:DocumentObject.ЗапросСправки2НДФЛСотрудником</v8:Type>
				<v8:Type>cfg:DocumentObject.РегистрацияПрочихДоходов</v8:Type>
				<v8:Type>cfg:CatalogObject.ОснованияДосрочногоНазначенияПенсииДляСЗВК</v8:Type>
				<v8:Type>cfg:CatalogObject.ВакансииПрисоединенныеФайлы</v8:Type>
				<v8:Type>cfg:DocumentObject.ИсходящаяСправкаОЗаработкеДляРасчетаПособий</v8:Type>
				<v8:Type>cfg:DocumentObject.ЗаявкаНаВключениеВКадровыйРезерв</v8:Type>
				<v8:Type>cfg:CatalogObject.ВедомостьПрочихДоходовПеречислениемПрисоединенныеФайлы</v8:Type>
				<v8:Type>cfg:DocumentObject.ПачкаДокументовСЗВ_6_3</v8:Type>
				<v8:Type>cfg:CatalogObject.ЗаявлениеИЗапросВПФРОЗаработкеПрисоединенныеФайлы</v8:Type>
				<v8:Type>cfg:CatalogObject.СведенияДляФРМОПрисоединенныеФайлы</v8:Type>
				<v8:Type>cfg:DocumentObject.РегистрацияСведенийОЗастрахованномЛицеФСС</v8:Type>
				<v8:Type>cfg:CatalogObject.ЗначенияХарактеристикПерсонала</v8:Type>
				<v8:Type>cfg:DocumentObject.ЭлектронноеПисьмоВходящее</v8:Type>
				<v8:Type>cfg:CatalogObject.ЭтапыРаботыСКандидатами</v8:Type>
				<v8:Type>cfg:CatalogObject.СтепениРодстваФизическихЛиц</v8:Type>
				<v8:Type>cfg:CatalogObject.РезультатыАттестацииСотрудниковПрисоединенныеФайлы</v8:Type>
				<v8:Type>cfg:DocumentObject.ПереносЗатратНаПерсоналМеждуСтатьями</v8:Type>
				<v8:Type>cfg:DocumentObject.ПереводНаРаботуСКоронавирусом</v8:Type>
				<v8:Type>cfg:DocumentObject.ВедомостьНаВыплатуЗарплатыВБанк</v8:Type>
				<v8:Type>cfg:DocumentObject.ИзменениеГрафикаРаботыСписком</v8:Type>
				<v8:Type>cfg:DocumentObject.ЗаявкаНаКомандировку</v8:Type>
				<v8:Type>cfg:CatalogObject.ЗапросСправки2НДФЛСотрудникомПрисоединенныеФайлы</v8:Type>
				<v8:Type>cfg:DocumentObject.ЗаявлениеСотрудникаНаВыплатуПособия</v8:Type>
				<v8:Type>cfg:DocumentObject.РасходыНаИсточникИнформацииОКандидатах</v8:Type>
				<v8:Type>cfg:CatalogObject.УтверждениеТарифнойСеткиПрисоединенныеФайлы</v8:Type>
				<v8:Type>cfg:CatalogObject.ДанныеДляРасчетаЗарплатыПрисоединенныеФайлы</v8:Type>
				<v8:Type>cfg:CatalogObject.ПричиныУвольнений</v8:Type>
				<v8:Type>cfg:DocumentObject.ПриказНаДоплатуДоСреднегоЗаработка</v8:Type>
				<v8:Type>cfg:CatalogObject.ПрофилиДолжностей</v8:Type>
				<v8:Type>cfg:CatalogObject.ОценкиОбучения</v8:Type>
				<v8:Type>cfg:CatalogObject.СреднийЗаработокСЭДОПрисоединенныеФайлы</v8:Type>
				<v8:Type>cfg:CatalogObject.СтатусыНалогоплательщиковПоНДФЛ</v8:Type>
				<v8:Type>cfg:CatalogObject.ИзменениеУсловийИсполнительногоЛистаПрисоединенныеФайлы</v8:Type>
				<v8:Type>cfg:CatalogObject.ОтпускПоУходуЗаРебенкомПрисоединенныеФайлы</v8:Type>
				<v8:Type>cfg:DocumentObject.ПланПоказателейЭффективностиПозиции</v8:Type>
				<v8:Type>cfg:CatalogObject.ИзменениеКвалификационногоРазрядаПрисоединенныеФайлы</v8:Type>
				<v8:Type>cfg:CatalogObject.Сценарии</v8:Type>
				<v8:Type>cfg:CatalogObject.ЯзыкиНародовМира</v8:Type>
				<v8:Type>cfg:DocumentObject.ПериодыОтсутствияСотрудников</v8:Type>
				<v8:Type>cfg:DocumentObject.ОтпускБезСохраненияОплатыСписком</v8:Type>
				<v8:Type>cfg:DocumentObject.НазначениеПодработки</v8:Type>
				<v8:Type>cfg:DocumentObject.ИсходящееСообщениеОСтраховомСлучаеФСС</v8:Type>
				<v8:Type>cfg:CatalogObject.ВидыОбщественноПолезнойДеятельностиСЗВК</v8:Type>
				<v8:Type>cfg:DocumentObject.ИсключениеИзКадровогоРезерва</v8:Type>
				<v8:Type>cfg:CatalogObject.ПогашениеЗадолженностиПоВзысканиямПрисоединенныеФайлы</v8:Type>
				<v8:Type>cfg:CatalogObject.ВидыЗаявокНаЕдиновременнуюКомпенсациюСотрудникам</v8:Type>
				<v8:Type>cfg:DocumentObject.ПростойСотрудников</v8:Type>
				<v8:Type>cfg:DocumentObject.ЕдиновременноеПособиеЗаСчетФСС</v8:Type>
				<v8:Type>cfg:DocumentObject.ПродлениеКонтрактаДоговора</v8:Type>
				<v8:Type>cfg:CatalogObject.ПериодыОтсутствияСотрудниковПрисоединенныеФайлы</v8:Type>
				<v8:Type>cfg:CatalogObject.ПравилаОбработкиЭлектроннойПочты</v8:Type>
				<v8:Type>cfg:DocumentObject.УдержаниеВСчетРасчетовПоПрочимОперациям</v8:Type>
				<v8:Type>cfg:CatalogObject.СведенияОЗастрахованномЛицеФССПрисоединенныеФайлы</v8:Type>
				<v8:Type>cfg:CatalogObject.РешенияПоКадровымИзменениямПрисоединенныеФайлы</v8:Type>
				<v8:Type>cfg:CatalogObject.НастройкиРасчетаРезервовПоОплатеТруда</v8:Type>
				<v8:Type>cfg:CatalogObject.ШтатноеРасписание</v8:Type>
				<v8:Type>cfg:DocumentObject.ПодтверждениеОткрытияЛицевыхСчетовСотрудников</v8:Type>
				<v8:Type>cfg:DocumentObject.ОтгулСписком</v8:Type>
				<v8:Type>cfg:CatalogObject.РегламентированныйОтчетПрисоединенныеФайлы</v8:Type>
				<v8:Type>cfg:DocumentObject.ПачкаДокументовАДВ_2</v8:Type>
				<v8:Type>cfg:CatalogObject.ПереводНаОплатуПоСреднемуЗаработкуПрисоединенныеФайлы</v8:Type>
				<v8:Type>cfg:CatalogObject.МатериальнаяПомощьПрисоединенныеФайлы</v8:Type>
				<v8:Type>cfg:CatalogObject.УчетныеЗаписиВидеоконференций</v8:Type>
				<v8:Type>cfg:DocumentObject.ОтражениеРасходовНаПерсонал</v8:Type>
				<v8:Type>cfg:DocumentObject.СогласиеНаПрисоединениеККЭДО</v8:Type>
				<v8:Type>cfg:CatalogObject.ЭлектронныеРесурсы</v8:Type>
				<v8:Type>cfg:CatalogObject.РазовоеНачислениеПрисоединенныеФайлы</v8:Type>
				<v8:Type>cfg:CatalogObject.ОтражениеУдержанногоНДФЛВБухучетеПрисоединенныеФайлы</v8:Type>
				<v8:Type>cfg:CatalogObject.МедицинскиеОрганизации</v8:Type>
				<v8:Type>cfg:CatalogObject.ПараметрыИсчисляемогоСтраховогоСтажа</v8:Type>
				<v8:Type>cfg:CatalogObject.ВидыРасчетовРезервовПоОплатеТруда</v8:Type>
				<v8:Type>cfg:DocumentObject.ЗаявкаНаЕдиновременнуюКомпенсацию</v8:Type>
				<v8:Type>cfg:CatalogObject.ВредныеОпасныеПроизводственныеФакторы</v8:Type>
				<v8:Type>cfg:CatalogObject.НесоответствиеСведенийОЗастрахованномЛицеСЭДОПрисоединенныеФайлы</v8:Type>
				<v8:Type>cfg:DocumentObject.ОперацияУчетаПоСтраховымВзносам</v8:Type>
				<v8:Type>cfg:DocumentObject.СправкиНДФЛДляПередачиВНалоговыйОрган</v8:Type>
				<v8:Type>cfg:DocumentObject.РегистрацияПереработок</v8:Type>
				<v8:Type>cfg:DocumentObject.ДоходВНатуральнойФорме</v8:Type>
				<v8:Type>cfg:CatalogObject.ПриостановлениеТрудовыхДоговоровКонтрактовПрисоединенныеФайлы</v8:Type>
				<v8:Type>cfg:DocumentObject.ИзменениеУсловийМедицинскогоСтрахования</v8:Type>
				<v8:Type>cfg:DocumentObject.СведенияОТрудовойДеятельностиРаботниковСЗВ_ТД</v8:Type>
				<v8:Type>cfg:DocumentObject.ИзменениеУсловийИсполнительногоЛиста</v8:Type>
				<v8:Type>cfg:DocumentObject.ПланОбученияРазвития</v8:Type>
				<v8:Type>cfg:DocumentObject.ЗаявлениеИЗапросВПФРОЗаработке</v8:Type>
				<v8:Type>cfg:CatalogObject.ВидыПредоставляемыхСотрудникамСправокПрисоединенныеФайлы</v8:Type>
				<v8:Type>cfg:CatalogObject.ПачкаДокументовСПВ_2ПрисоединенныеФайлы</v8:Type>
				<v8:Type>cfg:DocumentObject.ЗапросСреднегоЗаработкаСЭДО</v8:Type>
				<v8:Type>cfg:CatalogObject.СведенияДляИсчисленияДоплатыКПенсииСЗВ_ДСОПрисоединенныеФайлы</v8:Type>
				<v8:Type>cfg:DocumentObject.ХодатайствоОБронированииГражданПребывающихВЗапасе</v8:Type>
				<v8:Type>cfg:DocumentObject.ПлатежноеПоручение</v8:Type>
				<v8:Type>cfg:CatalogObject.ОписьЗаявленийСотрудниковНаВыплатуПособийПрисоединенныеФайлы</v8:Type>
				<v8:Type>cfg:CatalogObject.ВидыОперацийРасчетаЗарплаты</v8:Type>
				<v8:Type>cfg:CatalogObject.БроньПрисоединенныеФайлы</v8:Type>
				<v8:Type>cfg:CatalogObject.НазначениеПлановогоНачисленияПрисоединенныеФайлы</v8:Type>
				<v8:Type>cfg:CatalogObject.Мотиваторы</v8:Type>
				<v8:Type>cfg:DocumentObject.ПланПоказателейЭффективностиСотрудника</v8:Type>
				<v8:Type>cfg:DocumentObject.ОтменаСовмещения</v8:Type>
				<v8:Type>cfg:CatalogObject.КомпенсацияЗаЗадержкуЗарплатыПрисоединенныеФайлы</v8:Type>
				<v8:Type>cfg:CatalogObject.ПачкаДокументовСЗВ_6_4ПрисоединенныеФайлы</v8:Type>
				<v8:Type>cfg:CatalogObject.СообщениеОбОтсутствииПрисоединенныеФайлы</v8:Type>
				<v8:Type>cfg:CatalogObject.ГруппыВнешнихПользователей</v8:Type>
				<v8:Type>cfg:CatalogObject.Валюты</v8:Type>
				<v8:Type>cfg:CatalogObject.КритерииОценкиПозицийШтатногоРасписания</v8:Type>
				<v8:Type>cfg:DocumentObject.ЗаявкаНаОткрытиеЛицевыхСчетовСотрудников</v8:Type>
				<v8:Type>cfg:DocumentObject.СогласиеНаУведомлениеОбЭЛН</v8:Type>
				<v8:Type>cfg:DocumentObject.ИзменениеУсловийОплатыОтпускаПоУходуЗаРебенком</v8:Type>
				<v8:Type>cfg:CatalogObject.ВозмещениеБольничныхВЧастиФБПрисоединенныеФайлы</v8:Type>
				<v8:Type>cfg:CatalogObject.ДокументКадровогоЭДОПрисоединенныеФайлы</v8:Type>
				<v8:Type>cfg:CatalogObject.СведенияОНезачисленнойЗарплатеПрисоединенныеФайлы</v8:Type>
				<v8:Type>cfg:CatalogObject.ГрафикОтпусковПрисоединенныеФайлы</v8:Type>
				<v8:Type>cfg:DocumentObject.КадровыйПереводСписком</v8:Type>
				<v8:Type>cfg:DocumentObject.ПостоянноеУдержаниеВПользуТретьихЛиц</v8:Type>
				<v8:Type>cfg:CatalogObject.Чатботы</v8:Type>
				<v8:Type>cfg:CatalogObject.ДоходВНатуральнойФормеПрисоединенныеФайлы</v8:Type>
				<v8:Type>cfg:CatalogObject.КомплектыОтчетностиПерсУчетаПрисоединенныеФайлы</v8:Type>
				<v8:Type>cfg:CatalogObject.ВедомостьУплатыАДВ_11ПрисоединенныеФайлы</v8:Type>
				<v8:Type>cfg:DocumentObject.ЗаявлениеНаПредоставлениеСтандартныхВычетовПоНДФЛ</v8:Type>
				<v8:Type>cfg:CatalogObject.ОтпускПрисоединенныеФайлы</v8:Type>
				<v8:Type>cfg:CatalogObject.НачальнаяШтатнаяРасстановкаПрисоединенныеФайлы</v8:Type>
				<v8:Type>cfg:CatalogObject.РаботаСверхурочноПрисоединенныеФайлы</v8:Type>
				<v8:Type>cfg:CatalogObject.БанковскиеКартыКонтрагентов</v8:Type>
				<v8:Type>cfg:CatalogObject.ПодтверждениеОткрытияЛицевыхСчетовСотрудниковПрисоединенныеФайлы</v8:Type>
				<v8:Type>cfg:CatalogObject.УвольнениеСпискомПрисоединенныеФайлы</v8:Type>
				<v8:Type>cfg:CatalogObject.Сотрудники</v8:Type>
				<v8:Type>cfg:CatalogObject.ГрафикУчетаСамочувствияСотрудников</v8:Type>
				<v8:Type>cfg:CatalogObject.ПланПоказателейЭффективностиПодразделенияПрисоединенныеФайлы</v8:Type>
				<v8:Type>cfg:DocumentObject.НачальнаяЗадолженностьПоЗарплате</v8:Type>
				<v8:Type>cfg:DocumentObject.Совмещение</v8:Type>
				<v8:Type>cfg:DocumentObject.ПерерасчетСтраховыхВзносов</v8:Type>
				<v8:Type>cfg:ChartOfCharacteristicTypesObject.ДолжностиПодключаемыеХарактеристики</v8:Type>
				<v8:Type>cfg:CatalogObject.ИсточникиИнформацииОКандидатах</v8:Type>
				<v8:Type>cfg:CatalogObject.СостоянияОригиналовПервичныхДокументов</v8:Type>
				<v8:Type>cfg:CatalogObject.ТерриторииВыполненияРабот</v8:Type>
				<v8:Type>cfg:CatalogObject.ЗамещениеГосударственныхМуниципальныхДолжностейПФР</v8:Type>
				<v8:Type>cfg:DocumentObject.ОтзывСогласияНаОбработкуПерсональныхДанных</v8:Type>
				<v8:Type>cfg:CatalogObject.ОснованияУвольненияПользовательские</v8:Type>
				<v8:Type>cfg:CatalogObject.ОписьОДВ_1ПрисоединенныеФайлы</v8:Type>
				<v8:Type>cfg:DocumentObject.СведенияОПриемеПереводеИУвольненииДляВоенкомата</v8:Type>
				<v8:Type>cfg:DocumentObject.ВозмещениеРасходовФондомСоциальногоСтрахования</v8:Type>
				<v8:Type>cfg:DocumentObject.СписаниеДепонированнойЗарплаты</v8:Type>
				<v8:Type>cfg:CatalogObject.ПоставщикиЭлектронныхКурсов</v8:Type>
				<v8:Type>cfg:CatalogObject.ОснованияУвольнения</v8:Type>
				<v8:Type>cfg:ChartOfCharacteristicTypesObject.ДополнительныеРеквизитыИСведения</v8:Type>
				<v8:Type>cfg:DocumentObject.ВыплатыПоДоговорамОпеки</v8:Type>
				<v8:Type>cfg:CatalogObject.ДополнительныеОтчетыИОбработки</v8:Type>
				<v8:Type>cfg:DocumentObject.ВходящаяСправкаОЗаработкеДляРасчетаПособий</v8:Type>
				<v8:Type>cfg:CatalogObject.ВводНачальныхОстатковОтпусковПрисоединенныеФайлы</v8:Type>
				<v8:Type>cfg:DocumentObject.БольничныйЛист</v8:Type>
				<v8:Type>cfg:DocumentObject.Командировка</v8:Type>
				<v8:Type>cfg:CatalogObject.ЭкземплярыСервераDSS</v8:Type>
				<v8:Type>cfg:CatalogObject.ВидыПроцедурАккредитацииСпециалистов</v8:Type>
				<v8:Type>cfg:DocumentObject.ПериодыОплаченныеДоНачалаЭксплуатации</v8:Type>
				<v8:Type>cfg:CatalogObject.ПланОбученияРазвитияПрисоединенныеФайлы</v8:Type>
				<v8:Type>cfg:DocumentObject.КомандировкиСотрудников</v8:Type>
				<v8:Type>cfg:CatalogObject.ОсобыеУсловияТрудаПФР</v8:Type>
				<v8:Type>cfg:CatalogObject.УчебныеЗаведения</v8:Type>
				<v8:Type>cfg:DocumentObject.ДекларацияСоответствияУсловийТруда</v8:Type>
				<v8:Type>cfg:CatalogObject.Награды</v8:Type>
				<v8:Type>cfg:CatalogObject.ОтзывСогласияНаУведомлениеОбЭЛНПрисоединенныеФайлы</v8:Type>
				<v8:Type>cfg:CatalogObject.Грейды</v8:Type>
				<v8:Type>cfg:DocumentObject.ОтражениеЗарплатыВФинансовомУчете</v8:Type>
				<v8:Type>cfg:CatalogObject.ВозвратНДФЛПрисоединенныеФайлы</v8:Type>
				<v8:Type>cfg:DocumentObject.СведенияДляФРМО</v8:Type>
				<v8:Type>cfg:DocumentObject.ВедомостьПрочихДоходовВБанк</v8:Type>
				<v8:Type>cfg:CatalogObject.ТабельУчетаРабочегоВремениПрисоединенныеФайлы</v8:Type>
				<v8:Type>cfg:DocumentObject.НесоответствиеСведенийОЗастрахованномЛицеСЭДО</v8:Type>
				<v8:Type>cfg:DocumentObject.ПрикреплениеКПрограммамМедицинскогоСтрахования</v8:Type>
				<v8:Type>cfg:DocumentObject.НачислениеЗарплаты</v8:Type>
				<v8:Type>cfg:DocumentObject.ПачкаДокументовАДВ_1</v8:Type>
				<v8:Type>cfg:DocumentObject.СведенияОЗастрахованномЛицеФСС</v8:Type>
				<v8:Type>cfg:DocumentObject.РеестрДСВ_3</v8:Type>
				<v8:Type>cfg:DocumentObject.ЗапланированноеВзаимодействие</v8:Type>
				<v8:Type>cfg:CatalogObject.ЗаявкаНаОткрытиеЛицевыхСчетовСотрудниковПрисоединенныеФайлы</v8:Type>
				<v8:Type>cfg:DocumentObject.КадровыйПлан</v8:Type>
				<v8:Type>cfg:CatalogObject.ПланРасходовНаПерсоналПрисоединенныеФайлы</v8:Type>
				<v8:Type>cfg:CatalogObject.СертификатыКлючейЭлектроннойПодписиИШифрования</v8:Type>
				<v8:Type>cfg:DocumentObject.ПереводНаОплатуПоСреднемуЗаработку</v8:Type>
				<v8:Type>cfg:CatalogObject.ВключениеВКадровыйРезервПрисоединенныеФайлы</v8:Type>
				<v8:Type>cfg:CatalogObject.РеестрДанныхЭЛНЗаполняемыхРаботодателемПрисоединенныеФайлы</v8:Type>
				<v8:Type>cfg:CatalogObject.ОснованияДосрочногоНазначенияПенсии</v8:Type>
				<v8:Type>cfg:CatalogObject.БанковскиеСчетаКонтрагентов</v8:Type>
				<v8:Type>cfg:CatalogObject.ПроизвольныйКадровыйПриказПрисоединенныеФайлы</v8:Type>
				<v8:Type>cfg:DocumentObject.ВыплатаДепонированнойЗарплаты</v8:Type>
				<v8:Type>cfg:CatalogObject.ОтменаЗаявкиНаКомандировкуПрисоединенныеФайлы</v8:Type>
				<v8:Type>cfg:CatalogObject.АктПроверкиСтраховыхВзносовПрисоединенныеФайлы</v8:Type>
				<v8:Type>cfg:CatalogObject.СведенияОЗастрахованныхЛицахСЗВ_МПрисоединенныеФайлы</v8:Type>
				<v8:Type>cfg:CatalogObject.ЗаявлениеВФССОВозмещенииВыплатРодителямДетейИнвалидовПрисоединенныеФайлы</v8:Type>
				<v8:Type>cfg:CatalogObject.СтруктураПредприятия</v8:Type>
				<v8:Type>cfg:DocumentObject.Отгул</v8:Type>
				<v8:Type>cfg:CatalogObject.ТрудовыеФункции</v8:Type>
				<v8:Type>cfg:CatalogObject.ПродлениеКонтрактаДоговораПрисоединенныеФайлы</v8:Type>
				<v8:Type>cfg:CatalogObject.БольничныйЛистПрисоединенныеФайлы</v8:Type>
				<v8:Type>cfg:CatalogObject.СписаниеДепонированнойЗарплатыПрисоединенныеФайлы</v8:Type>
				<v8:Type>cfg:CatalogObject.ВидыОтпусков</v8:Type>
				<v8:Type>cfg:CatalogObject.ПредопределенныеВариантыОтчетов</v8:Type>
				<v8:Type>cfg:CatalogObject.ДекларацияСоответствияУсловийТрудаПрисоединенныеФайлы</v8:Type>
				<v8:Type>cfg:CatalogObject.ПачкаДокументовСЗВ_КПрисоединенныеФайлы</v8:Type>
				<v8:Type>cfg:CatalogObject.СтруктураЦелей</v8:Type>
				<v8:Type>cfg:DocumentObject.НазначениеПоказателейЭффективности</v8:Type>
				<v8:Type>cfg:CatalogObject.НаправлениеНаМедицинскийОсмотрПрисоединенныеФайлы</v8:Type>
				<v8:Type>cfg:CatalogObject.ВидыДеятельностиСпециалистов</v8:Type>
				<v8:Type>cfg:CatalogObject.ОперацияУчетаПоСтраховымВзносамПрисоединенныеФайлы</v8:Type>
				<v8:Type>cfg:DocumentObject.ПачкаДокументовСЗВ_К</v8:Type>
				<v8:Type>cfg:CatalogObject.ВидыКонтактнойИнформации</v8:Type>
				<v8:Type>cfg:CatalogObject.ПоследствияНесчастныхСлучаев</v8:Type>
				<v8:Type>cfg:CatalogObject.ВходящаяСправкаОЗаработкеДляРасчетаПособийПрисоединенныеФайлы</v8:Type>
				<v8:Type>cfg:CatalogObject.ЗаключениеМедицинскогоОсмотраПрисоединенныеФайлы</v8:Type>
				<v8:Type>cfg:CatalogObject.НаправленияДеятельности</v8:Type>
				<v8:Type>cfg:CatalogObject.ДоговорАвторскогоЗаказаПрисоединенныеФайлы</v8:Type>
				<v8:Type>cfg:CatalogObject.РегистрацияПрочихДоходовПрисоединенныеФайлы</v8:Type>
				<v8:Type>cfg:DocumentObject.Анкета</v8:Type>
				<v8:Type>cfg:CatalogObject.РассылкиУведомлений</v8:Type>
				<v8:Type>cfg:DocumentObject.ДоговорАвторскогоЗаказа</v8:Type>
				<v8:Type>cfg:DocumentObject.ФактПоказателейЭффективностиПодразделения</v8:Type>
				<v8:Type>cfg:CatalogObject.ВедомостьНаВыплатуЗарплатыВКассуПрисоединенныеФайлы</v8:Type>
				<v8:Type>cfg:DocumentObject.ПрекращениеПодработки</v8:Type>
				<v8:Type>cfg:DocumentObject.УдержаниеПрофсоюзныхВзносов</v8:Type>
				<v8:Type>cfg:CatalogObject.ЗаявкаНаВключениеВПланОбученияПрисоединенныеФайлы</v8:Type>
				<v8:Type>cfg:CatalogObject.СведенияОЗаработкеСтажеЗастрахованныхЛицСЗВ_ИСХПрисоединенныеФайлы</v8:Type>
				<v8:Type>cfg:CatalogObject.ВозобновлениеТрудовыхДоговоровКонтрактовПрисоединенныеФайлы</v8:Type>
				<v8:Type>cfg:CatalogObject.ВнешниеПользователи</v8:Type>
				<v8:Type>cfg:CatalogObject.РегистрацияТрудовойДеятельностиПрисоединенныеФайлы</v8:Type>
				<v8:Type>cfg:DocumentObject.ВключениеВКадровыйРезерв</v8:Type>
				<v8:Type>cfg:CatalogObject.РаспределениеРасходовНаПерсоналПрисоединенныеФайлы</v8:Type>
				<v8:Type>cfg:CatalogObject.РешениеОбОтпускеПоУходуЗаРебенкомПрисоединенныеФайлы</v8:Type>
				<v8:Type>cfg:DocumentObject.ФактПоказателяЭффективностиСотрудников</v8:Type>
				<v8:Type>cfg:CatalogObject.ВозмещениеРасходовФондомСоциальногоСтрахованияПрисоединенныеФайлы</v8:Type>
				<v8:Type>cfg:CatalogObject.ЗаявкаНаКомандировкуПрисоединенныеФайлы</v8:Type>
				<v8:Type>cfg:CatalogObject.ЗванияГражданскогоВоинскогоУчета</v8:Type>
				<v8:Type>cfg:CatalogObject.КлассификаторыФедеральныхМедрегистров</v8:Type>
				<v8:Type>cfg:CatalogObject.ЗначенияСвойствОбъектов</v8:Type>
				<v8:Type>cfg:DocumentObject.ЗаявкаНаВключениеВПланОбучения</v8:Type>
				<v8:Type>cfg:CatalogObject.ЗначенияСвойствОбъектовИерархия</v8:Type>
				<v8:Type>cfg:CatalogObject.ТестовыеВопросы</v8:Type>
				<v8:Type>cfg:CatalogObject.ГруппыДоступа</v8:Type>
				<v8:Type>cfg:CatalogObject.РодственникиФизическихЛиц</v8:Type>
				<v8:Type>cfg:CatalogObject.ПравилаИнтеграцииС1СДокументооборотом</v8:Type>
				<v8:Type>cfg:CatalogObject.ВопросыДляСобеседования</v8:Type>
				<v8:Type>cfg:DocumentObject.НачислениеЗаПервуюПоловинуМесяца</v8:Type>
				<v8:Type>cfg:DocumentObject.ПогашениеЗадолженностиПоВзысканиям</v8:Type>
				<v8:Type>cfg:DocumentObject.Отпуск</v8:Type>
				<v8:Type>cfg:DocumentObject.ПланПоказателейЭффективностиПодразделения</v8:Type>
				<v8:Type>cfg:DocumentObject.СправкиПоНДФЛДляРасчетаПоНалогуНаПрибыль</v8:Type>
				<v8:Type>cfg:CatalogObject.МероприятияАдаптацииУвольнения</v8:Type>
				<v8:Type>cfg:CatalogObject.НаборыДополнительныхРеквизитовИСведений</v8:Type>
				<v8:Type>cfg:CatalogObject.СодержаниеЭлектронныхКурсов</v8:Type>
				<v8:Type>cfg:CatalogObject.ПроизводственныеКалендари</v8:Type>
				<v8:Type>cfg:DocumentObject.РеестрСЗВ_6_2</v8:Type>
				<v8:Type>cfg:CatalogObject.КадровыйПереводСпискомПрисоединенныеФайлы</v8:Type>
				<v8:Type>cfg:CatalogObject.РабочиеМестаОхраныТруда</v8:Type>
				<v8:Type>cfg:CatalogObject.СовмещениеПрисоединенныеФайлы</v8:Type>
				<v8:Type>cfg:CatalogObject.ОтменаЗаявкиНаЕдиновременнуюКомпенсациюПрисоединенныеФайлы</v8:Type>
				<v8:Type>cfg:CatalogObject.ЕдиновременноеПособиеЗаСчетФССПрисоединенныеФайлы</v8:Type>
				<v8:Type>cfg:CatalogObject.СпискиПрофессийДолжностейЛьготногоПенсионногоОбеспечения</v8:Type>
				<v8:Type>cfg:DocumentObject.ВедомостьУплатыАДВ_11</v8:Type>
				<v8:Type>cfg:DocumentObject.ОплатаПоСреднемуЗаработкуСписком</v8:Type>
				<v8:Type>cfg:CatalogObject.РеестрСведенийНеобходимыхДляНазначенияИВыплатыПособийПрисоединенныеФайлы</v8:Type>
				<v8:Type>cfg:DocumentObject.ИзменениеМестРаботы</v8:Type>
				<v8:Type>cfg:CatalogObject.ПоказателиПремирования</v8:Type>
				<v8:Type>cfg:CatalogObject.Работодатели</v8:Type>
				<v8:Type>cfg:CatalogObject.НачальныеРасчетыСБюджетомПоНДФЛПрисоединенныеФайлы</v8:Type>
				<v8:Type>cfg:CatalogObject.Файлы</v8:Type>
				<v8:Type>cfg:CatalogObject.ПродлениеИспытательногоСрокаПрисоединенныеФайлы</v8:Type>
				<v8:Type>cfg:DocumentObject.АвансовыйПлатежИностранцаПоНДФЛ</v8:Type>
				<v8:Type>cfg:CatalogObject.ИнструктажПоОхранеТрудаПрисоединенныеФайлы</v8:Type>
				<v8:Type>cfg:DocumentObject.ЗаявкаНаЗакрытиеЛицевыхСчетовСотрудников</v8:Type>
				<v8:Type>cfg:CatalogObject.ОтгулСпискомПрисоединенныеФайлы</v8:Type>
				<v8:Type>cfg:DocumentObject.ФактПоказателяЭффективностиПодразделений</v8:Type>
				<v8:Type>cfg:DocumentObject.СообщениеSMS</v8:Type>
				<v8:Type>cfg:CatalogObject.ЭлементыКлассификаторовФедеральныхМедрегистров</v8:Type>
				<v8:Type>cfg:BusinessProcessObject.ЗаданиеАдаптацииУвольнения</v8:Type>
				<v8:Type>cfg:DocumentObject.МатериальнаяПомощь</v8:Type>
				<v8:Type>cfg:DocumentObject.СведенияДляФРМР</v8:Type>
				<v8:Type>cfg:DocumentObject.РегистрацияТрудовойДеятельности</v8:Type>
				<v8:Type>cfg:CatalogObject.КомпетенцииПерсонала</v8:Type>
				<v8:Type>cfg:CatalogObject.ВыплатыПоДоговорамОпекиПрисоединенныеФайлы</v8:Type>
				<v8:Type>cfg:CatalogObject.ШтатноеРасписаниеПрисоединенныеФайлы</v8:Type>
				<v8:Type>cfg:DocumentObject.СторнированиеНачислений</v8:Type>
				<v8:Type>cfg:CatalogObject.СправкаНДФЛПрисоединенныеФайлы</v8:Type>
				<v8:Type>cfg:CatalogObject.АктПриемкиВыполненныхРаботОказанныхУслугПрисоединенныеФайлы</v8:Type>
				<v8:Type>cfg:DocumentObject.ДоговорЗаймаСотруднику</v8:Type>
				<v8:Type>cfg:CatalogObject.ВыплатаДепонированнойЗарплатыПрисоединенныеФайлы</v8:Type>
				<v8:Type>cfg:CatalogObject.ИзменениеУсловийДоговораЗаймаСотрудникуПрисоединенныеФайлы</v8:Type>
				<v8:Type>cfg:CatalogObject.ПачкаРазделов6РасчетаРСВ_1ПрисоединенныеФайлы</v8:Type>
				<v8:Type>cfg:CatalogObject.ЭлектронноеПисьмоИсходящееПрисоединенныеФайлы</v8:Type>
				<v8:Type>cfg:CatalogObject.ШаблоныСообщенийПрисоединенныеФайлы</v8:Type>
				<v8:Type>cfg:DocumentObject.ПриемНаРаботу</v8:Type>
				<v8:Type>cfg:DocumentObject.ИзменениеПлановыхНачислений</v8:Type>
				<v8:Type>cfg:CatalogObject.ВариантыОтветовАнкет</v8:Type>
				<v8:Type>cfg:CatalogObject.Резервы</v8:Type>
				<v8:Type>cfg:CatalogObject.ОткреплениеОтПрограммМедицинскогоСтрахованияПрисоединенныеФайлы</v8:Type>
				<v8:Type>cfg:CatalogObject.ПлановоеНачислениеПрочихДоходовПрисоединенныеФайлы</v8:Type>
				<v8:Type>cfg:CatalogObject.РешениеОВосстановленииВДолжностиПрисоединенныеФайлы</v8:Type>
				<v8:Type>cfg:CatalogObject.ВедомостьНаВыплатуЗарплатыПеречислениемПрисоединенныеФайлы</v8:Type>
				<v8:Type>cfg:DocumentObject.СообщениеОбОтсутствии</v8:Type>
				<v8:Type>cfg:CatalogObject.КомандировкиСотрудниковПрисоединенныеФайлы</v8:Type>
				<v8:Type>cfg:CatalogObject.НачислениеЗаПервуюПоловинуМесяцаПрисоединенныеФайлы</v8:Type>
				<v8:Type>cfg:DocumentObject.ПлановоеНачислениеПрочихДоходов</v8:Type>
				<v8:Type>cfg:DocumentObject.ПереносДанных</v8:Type>
				<v8:Type>cfg:DocumentObject.ОтветНаЗапросФССДляРасчетаПособия</v8:Type>
				<v8:Type>cfg:CatalogObject.ВидыДоговоровАвторскогоЗаказа</v8:Type>
				<v8:Type>cfg:CatalogObject.ПеречислениеНДФЛВБюджетПрисоединенныеФайлы</v8:Type>
				<v8:Type>cfg:DocumentObject.ДокументКадровогоЭДО</v8:Type>
				<v8:Type>cfg:CatalogObject.РасходыНаИсточникИнформацииОКандидатахПрисоединенныеФайлы</v8:Type>
				<v8:Type>cfg:CatalogObject.ИзменениеШтатногоРасписанияПрисоединенныеФайлы</v8:Type>
				<v8:Type>cfg:CatalogObject.ИсходящееСообщениеОСтраховомСлучаеФССПрисоединенныеФайлы</v8:Type>
				<v8:Type>cfg:CatalogObject.ЗапланированноеВзаимодействиеПрисоединенныеФайлы</v8:Type>
				<v8:Type>cfg:DocumentObject.ТелефонныйЗвонок</v8:Type>
				<v8:Type>cfg:DocumentObject.ДепонированиеЗарплаты</v8:Type>
				<v8:Type>cfg:ChartOfCalculationTypesObject.Удержания</v8:Type>
				<v8:Type>cfg:CatalogObject.ОтменаСовмещенияПрисоединенныеФайлы</v8:Type>
				<v8:Type>cfg:CatalogObject.УченыеСтепени</v8:Type>
				<v8:Type>cfg:DocumentObject.УдержаниеДобровольныхВзносовВНПФ</v8:Type>
				<v8:Type>cfg:CatalogObject.ВопросыШаблонаАнкеты</v8:Type>
				<v8:Type>cfg:DocumentObject.ПрогулНеявка</v8:Type>
				<v8:Type>cfg:DocumentObject.Увольнение</v8:Type>
				<v8:Type>cfg:CatalogObject.ТерминыЭлектронныхГлоссариев</v8:Type>
				<v8:Type>cfg:CatalogObject.УчетныеЗаписиDSS</v8:Type>
				<v8:Type>cfg:CatalogObject.ЗапросСреднегоЗаработкаСЭДОПрисоединенныеФайлы</v8:Type>
				<v8:Type>cfg:DocumentObject.СогласиеНаОбработкуПерсональныхДанных</v8:Type>
				<v8:Type>cfg:CatalogObject.ВедомостьНаВыплатуЗарплатыВБанкПрисоединенныеФайлы</v8:Type>
				<v8:Type>cfg:DocumentObject.ПачкаДокументовСЗВ_6_4</v8:Type>
				<v8:Type>cfg:CatalogObject.ПрофессиональныеСтандарты</v8:Type>
				<v8:Type>cfg:DocumentObject.ОтменаЗаявкиНаЕдиновременнуюКомпенсацию</v8:Type>
				<v8:Type>cfg:DocumentObject.ОтзывЗаявленийОПредоставленииСведенийОТрудовойДеятельности</v8:Type>
				<v8:Type>cfg:CatalogObject.ЭлектронноеПисьмоВходящееПрисоединенныеФайлы</v8:Type>
				<v8:Type>cfg:CatalogObject.ВидыВычетовНДФЛ</v8:Type>
				<v8:Type>cfg:DocumentObject.АктПриемкиВыполненныхРаботОказанныхУслуг</v8:Type>
				<v8:Type>cfg:DocumentObject.ПланРасходовНаПерсонал</v8:Type>
				<v8:Type>cfg:CatalogObject.ИдентификаторыОбъектовМетаданных</v8:Type>
				<v8:Type>cfg:DocumentObject.УведомлениеОПравеНаИмущественныйВычетДляНДФЛ</v8:Type>
				<v8:Type>cfg:DocumentObject.РезультатыСпецоценкиУсловийТруда</v8:Type>
				<v8:Type>cfg:CatalogObject.ВариантыОтчетов</v8:Type>
				<v8:Type>cfg:CatalogObject.Вакансии</v8:Type>
				<v8:Type>cfg:CatalogObject.ЗаявкаНаВключениеВКадровыйРезервПрисоединенныеФайлы</v8:Type>
				<v8:Type>cfg:CatalogObject.ВидыДокументовФизическихЛиц</v8:Type>
				<v8:Type>cfg:CatalogObject.ИзменениеМестРаботыПрисоединенныеФайлы</v8:Type>
				<v8:Type>cfg:DocumentObject.ВедомостьПрочихДоходовПеречислением</v8:Type>
				<v8:Type>cfg:CatalogObject.РегламентированныеОтчеты</v8:Type>
				<v8:Type>cfg:CatalogObject.СменыРаботыСотрудников</v8:Type>
				<v8:Type>cfg:DocumentObject.БухучетЗарплатыСотрудников</v8:Type>
				<v8:Type>cfg:CatalogObject.ПроектыПрисоединенныеФайлы</v8:Type>
				<v8:Type>cfg:CatalogObject.ПодразделенияОрганизаций</v8:Type>
				<v8:Type>cfg:DocumentObject.СведенияОСтраховомСтажеЗастрахованныхЛицСЗВ_СТАЖ</v8:Type>
				<v8:Type>cfg:CatalogObject.СведенияОРаботникахДляМедРегистраПрисоединенныеФайлы</v8:Type>
				<v8:Type>cfg:CatalogObject.ГруппыПользователей</v8:Type>
				<v8:Type>cfg:CatalogObject.РешениеОКадровомПереводеПрисоединенныеФайлы</v8:Type>
				<v8:Type>cfg:CatalogObject.РезультатыСпецоценкиУсловийТрудаПрисоединенныеФайлы</v8:Type>
				<v8:Type>cfg:DocumentObject.ПротоколОпросаУчастникаНесчастногоСлучая</v8:Type>
				<v8:Type>cfg:DocumentObject.СведенияОЗаработкеСтажеЗастрахованныхЛицСЗВ_ИСХ</v8:Type>
				<v8:Type>cfg:CatalogObject.ПрограммыЭлектроннойПодписиИШифрования</v8:Type>
				<v8:Type>cfg:CatalogObject.УведомлениеОПрекращенииОтпускаПоУходуЗаРебенкомПрисоединенныеФайлы</v8:Type>
				<v8:Type>cfg:CatalogObject.ВидыРаботМедицинскихОсмотров</v8:Type>
				<v8:Type>cfg:CatalogObject.ТерриториальныеУсловияПФР</v8:Type>
				<v8:Type>cfg:DocumentObject.ВводНачальныхОстатковОтпусков</v8:Type>
				<v8:Type>cfg:DocumentObject.ЗаявлениеОПодтвержденииПраваНаЗачетАвансовПоНДФЛ</v8:Type>
				<v8:Type>cfg:CatalogObject.ПриказОбАттестацииСотрудниковПрисоединенныеФайлы</v8:Type>
				<v8:Type>cfg:CatalogObject.ТарифныеСетки</v8:Type>
				<v8:Type>cfg:DocumentObject.УплатаСтраховыхВзносовВФонды</v8:Type>
				<v8:Type>cfg:CatalogObject.ЗаписиРабочегоКалендаря</v8:Type>
				<v8:Type>cfg:CatalogObject.СторнированиеНачисленийПрисоединенныеФайлы</v8:Type>
				<v8:Type>cfg:CatalogObject.ВедомостьПрочихДоходовВКассуПрисоединенныеФайлы</v8:Type>
				<v8:Type>cfg:CatalogObject.ЗаявкаНаЗакрытиеЛицевыхСчетовСотрудниковПрисоединенныеФайлы</v8:Type>
				<v8:Type>cfg:ChartOfCharacteristicTypesObject.ХарактеристикиПерсонала</v8:Type>
				<v8:Type>cfg:DocumentObject.ОтзывСогласияНаУведомлениеОбЭЛН</v8:Type>
				<v8:Type>cfg:DocumentObject.РешениеОКадровомПереводе</v8:Type>
				<v8:Type>cfg:CatalogObject.ВыдачаЗаймаСотрудникуПрисоединенныеФайлы</v8:Type>
				<v8:Type>cfg:CatalogObject.ЭлектронныеГлоссарии</v8:Type>
				<v8:Type>cfg:CatalogObject.ФактПоказателейЭффективностиСотрудникаПрисоединенныеФайлы</v8:Type>
				<v8:Type>cfg:CatalogObject.ПеремещениеМеждуТерриториямиПрисоединенныеФайлы</v8:Type>
				<v8:Type>cfg:CatalogObject.ЗаявкаНаОбучениеРазвитиеПрисоединенныеФайлы</v8:Type>
				<v8:Type>cfg:CatalogObject.ПричиныУвольненияПФР</v8:Type>
				<v8:Type>cfg:CatalogObject.ЛичныеДанныеКандидатов</v8:Type>
				<v8:Type>cfg:DocumentObject.СведенияОЗастрахованныхЛицахСЗВ_М</v8:Type>
				<v8:Type>cfg:DocumentObject.ОтменаБронированияГражданПребывающихВЗапасе</v8:Type>
				<v8:Type>cfg:CatalogObject.ПодтверждениеЗачисленияЗарплатыПрисоединенныеФайлы</v8:Type>
				<v8:Type>cfg:DocumentObject.ВыдачаЗаймаСотруднику</v8:Type>
				<v8:Type>cfg:CatalogObject.СведенияОСтраховомСтажеЗастрахованныхЛицСЗВ_СТАЖПрисоединенныеФайлы</v8:Type>
				<v8:Type>cfg:DocumentObject.ВходящийЗапросФССДляРасчетаПособия</v8:Type>
				<v8:Type>cfg:CatalogObject.ВидыДокументовОбОбразовании</v8:Type>
				<v8:Type>cfg:DocumentObject.РешениеОВосстановленииВДолжности</v8:Type>
				<v8:Type>cfg:CatalogObject.ОтветНаЗапросФССДляРасчетаПособияПрисоединенныеФайлы</v8:Type>
				<v8:Type>cfg:CatalogObject.ДействияСотрудников</v8:Type>
				<v8:Type>cfg:TaskObject.ЗадачаИсполнителя</v8:Type>
				<v8:Type>cfg:DocumentObject.Бронь</v8:Type>
				<v8:Type>cfg:CatalogObject.ДепонированиеЗарплатыПрисоединенныеФайлы</v8:Type>
				<v8:Type>cfg:DocumentObject.ВозвратНДФЛ</v8:Type>
				<v8:Type>cfg:CatalogObject.ИсключениеИзКадровогоРезерваПрисоединенныеФайлы</v8:Type>
				<v8:Type>cfg:CatalogObject.РолиИсполнителей</v8:Type>
				<v8:Type>cfg:CatalogObject.ПрограммыМедицинскогоСтрахования</v8:Type>
				<v8:Type>cfg:CatalogObject.ИндексацияШтатногоРасписанияПрисоединенныеФайлы</v8:Type>
				<v8:Type>cfg:DocumentObject.РегламентированныйОтчет</v8:Type>
				<v8:Type>cfg:CatalogObject.ПланПоказателейЭффективностиПозицииПрисоединенныеФайлы</v8:Type>
				<v8:Type>cfg:CatalogObject.ФактПоказателяЭффективностиСотрудниковПрисоединенныеФайлы</v8:Type>
				<v8:Type>cfg:CatalogObject.ВозвратИзОтпускаПоУходуЗаРебенкомПрисоединенныеФайлы</v8:Type>
				<v8:Type>cfg:CatalogObject.ПапкиЭлектронныхПисем</v8:Type>
				<v8:Type>cfg:DocumentObject.ПоследствияНесчастногоСлучая</v8:Type>
				<v8:Type>cfg:DocumentObject.ПланПоказателяЭффективностиПодразделений</v8:Type>
				<v8:Type>cfg:DocumentObject.ЭлектронноеПисьмоИсходящее</v8:Type>
				<v8:Type>cfg:DocumentObject.УведомлениеОСпецрежимахНалогообложения</v8:Type>
				<v8:Type>cfg:CatalogObject.ВосстановлениеВДолжностиПрисоединенныеФайлы</v8:Type>
				<v8:Type>cfg:DocumentObject.НачислениеПоДоговорам</v8:Type>
				<v8:Type>cfg:DocumentObject.ПодтверждениеЗачисленияЗарплаты</v8:Type>
				<v8:Type>cfg:CatalogObject.ИсходящаяСправкаОЗаработкеДляРасчетаПособийПрисоединенныеФайлы</v8:Type>
				<v8:Type>cfg:CatalogObject.СообщениеОНеправильныхДанныхСотрудникаПрисоединенныеФайлы</v8:Type>
				<v8:Type>cfg:CatalogObject.ВидыОбразованияФизическихЛиц</v8:Type>
				<v8:Type>cfg:DocumentObject.ФактПоказателейЭффективностиСотрудника</v8:Type>
				<v8:Type>cfg:CatalogObject.ОграничениеВзысканийПрисоединенныеФайлы</v8:Type>
				<v8:Type>cfg:CatalogObject.ПриемНаРаботуСпискомПрисоединенныеФайлы</v8:Type>
				<v8:Type>cfg:CatalogObject.ЗаявкаНаЕдиновременнуюКомпенсациюПрисоединенныеФайлы</v8:Type>
				<v8:Type>cfg:DocumentObject.ОтменаДоплатыДоСреднегоЗаработка</v8:Type>
				<v8:Type>cfg:CatalogObject.ПричиныОтсутствияСотрудников</v8:Type>
				<v8:Type>cfg:ChartOfCalculationTypesObject.Начисления</v8:Type>
				<v8:Type>cfg:CatalogObject.СверкаСВоеннымКомиссариатомПрисоединенныеФайлы</v8:Type>
				<v8:Type>cfg:CatalogObject.ГруппыСотрудников</v8:Type>
				<v8:Type>cfg:CatalogObject.Военкоматы</v8:Type>
				<v8:Type>cfg:DocumentObject.СведенияОТрудовойДеятельностиРаботникаСТД_Р</v8:Type>
				<v8:Type>cfg:CatalogObject.ЗаявлениеВФССОВозмещенииРасходовНаПогребениеПрисоединенныеФайлы</v8:Type>
				<v8:Type>cfg:CatalogObject.ПриемНаРаботуПрисоединенныеФайлы</v8:Type>
				<v8:Type>cfg:DocumentObject.ОтпускПоУходуЗаРебенком</v8:Type>
				<v8:Type>cfg:CatalogObject.ВедомостьНаВыплатуЗарплатыРаздатчикомПрисоединенныеФайлы</v8:Type>
				<v8:Type>cfg:DocumentObject.НачислениеОценочныхОбязательствПоОтпускам</v8:Type>
				<v8:Type>cfg:DocumentObject.ИзменениеУсловийДоговораЗаймаСотруднику</v8:Type>
				<v8:Type>cfg:CatalogObject.КлассификаторыМедРегистра</v8:Type>
				<v8:Type>cfg:DocumentObject.ПачкаДокументовСПВ_2</v8:Type>
				<v8:Type>cfg:DocumentObject.ВедомостьНаВыплатуЗарплатыВКассу</v8:Type>
				<v8:Type>cfg:CatalogObject.СведенияОШтатномРасписанииДляМедРегистраПрисоединенныеФайлы</v8:Type>
				<v8:Type>cfg:CatalogObject.Контрагенты</v8:Type>
				<v8:Type>cfg:DocumentObject.ВозмещениеБольничныхВЧастиФБ</v8:Type>
				<v8:Type>cfg:CatalogObject.НаправлениеНаВнешнююАттестациюПрисоединенныеФайлы</v8:Type>
				<v8:Type>cfg:CatalogObject.СогласиеНаПрисоединениеККЭДОПрисоединенныеФайлы</v8:Type>
				<v8:Type>cfg:DocumentObject.СверкаСДокументамиВоинскогоУчета</v8:Type>
				<v8:Type>cfg:CatalogObject.БухучетЗарплатыСотрудниковПрисоединенныеФайлы</v8:Type>
				<v8:Type>cfg:DocumentObject.ЗаявленияОПредоставленииСведенийОТрудовойДеятельности</v8:Type>
				<v8:Type>cfg:DocumentObject.ИзменениеАванса</v8:Type>
				<v8:Type>cfg:CatalogObject.ОтгулПрисоединенныеФайлы</v8:Type>
				<v8:Type>cfg:CatalogObject.Пользователи</v8:Type>
			</Source>
			<Event>BeforeDelete</Event>
			<Handler>CommonModule.ОбменДаннымиАвтономнаяРаботаЗарплатаКадрыСобытия.АвтономнаяРаботаРегистрацияУдаления</Handler>
		</Properties>
	</EventSubscription>
</MetaDataObject>