<?xml version="1.0" encoding="UTF-8"?>
<MetaDataObject xmlns="http://v8.1c.ru/8.3/MDClasses" xmlns:app="http://v8.1c.ru/8.2/managed-application/core" xmlns:cfg="http://v8.1c.ru/8.1/data/enterprise/current-config" xmlns:cmi="http://v8.1c.ru/8.2/managed-application/cmi" xmlns:ent="http://v8.1c.ru/8.1/data/enterprise" xmlns:lf="http://v8.1c.ru/8.2/managed-application/logform" xmlns:style="http://v8.1c.ru/8.1/data/ui/style" xmlns:sys="http://v8.1c.ru/8.1/data/ui/fonts/system" xmlns:v8="http://v8.1c.ru/8.1/data/core" xmlns:v8ui="http://v8.1c.ru/8.1/data/ui" xmlns:web="http://v8.1c.ru/8.1/data/ui/colors/web" xmlns:win="http://v8.1c.ru/8.1/data/ui/colors/windows" xmlns:xen="http://v8.1c.ru/8.3/xcf/enums" xmlns:xpr="http://v8.1c.ru/8.3/xcf/predef" xmlns:xr="http://v8.1c.ru/8.3/xcf/readable" xmlns:xs="http://www.w3.org/2001/XMLSchema" xmlns:xsi="http://www.w3.org/2001/XMLSchema-instance" version="2.18">
	<DefinedType uuid="667b3dc6-91d8-4758-8fbb-3be11869e1cc">
		<InternalInfo>
			<xr:GeneratedType name="DefinedType.ВладельцыАрхивируемыхОбъектовОтчетности" category="DefinedType">
				<xr:TypeId>23477bbe-6e34-4230-b563-88a3e69f2ae9</xr:TypeId>
				<xr:ValueId>7ef098b0-02b5-4777-8d68-23637fb5a96e</xr:ValueId>
			</xr:GeneratedType>
		</InternalInfo>
		<Properties>
			<Name>ВладельцыАрхивируемыхОбъектовОтчетности</Name>
			<Synonym>
				<v8:item>
					<v8:lang>ru</v8:lang>
					<v8:content>Владельцы архивируемых объектов отчетности</v8:content>
				</v8:item>
			</Synonym>
			<Comment/>
			<Type>
				<v8:Type>cfg:DocumentRef.ТранспортноеСообщение</v8:Type>
				<v8:Type>cfg:CatalogRef.ЭлектронныеПредставленияРегламентированныхОтчетов</v8:Type>
				<v8:Type>cfg:DocumentRef.ЗапросНаВыпискуИзЕГРЮЛ_ЕГРИП</v8:Type>
				<v8:Type>cfg:CatalogRef.ОтправкиРПН</v8:Type>
				<v8:Type>cfg:DocumentRef.ЗапросНаИнформационноеОбслуживаниеНалогоплательщика</v8:Type>
				<v8:Type>cfg:DocumentRef.ЗапросНаИнформационноеОбслуживаниеСтрахователя</v8:Type>
				<v8:Type>cfg:CatalogRef.ПерепискаСКонтролирующимиОрганами</v8:Type>
				<v8:Type>cfg:CatalogRef.ОписиИсходящихДокументовВНалоговыеОрганы</v8:Type>
				<v8:Type>cfg:CatalogRef.ОписиВходящихДокументовИзНалоговыхОрганов</v8:Type>
				<v8:Type>cfg:CatalogRef.ОтправкиФТС</v8:Type>
				<v8:Type>cfg:CatalogRef.ДокументыРеализацииПолномочийНалоговыхОрганов</v8:Type>
				<v8:Type>cfg:CatalogRef.ОтправкиФСРАР</v8:Type>
				<v8:Type>cfg:CatalogRef.ОтправкиФСС</v8:Type>
				<v8:Type>cfg:CatalogRef.СканированныеДокументыДляПередачиВЭлектронномВиде</v8:Type>
			</Type>
		</Properties>
	</DefinedType>
</MetaDataObject>