<?xml version="1.0" encoding="UTF-8"?>
<MetaDataObject xmlns="http://v8.1c.ru/8.3/MDClasses" xmlns:app="http://v8.1c.ru/8.2/managed-application/core" xmlns:cfg="http://v8.1c.ru/8.1/data/enterprise/current-config" xmlns:cmi="http://v8.1c.ru/8.2/managed-application/cmi" xmlns:ent="http://v8.1c.ru/8.1/data/enterprise" xmlns:lf="http://v8.1c.ru/8.2/managed-application/logform" xmlns:style="http://v8.1c.ru/8.1/data/ui/style" xmlns:sys="http://v8.1c.ru/8.1/data/ui/fonts/system" xmlns:v8="http://v8.1c.ru/8.1/data/core" xmlns:v8ui="http://v8.1c.ru/8.1/data/ui" xmlns:web="http://v8.1c.ru/8.1/data/ui/colors/web" xmlns:win="http://v8.1c.ru/8.1/data/ui/colors/windows" xmlns:xen="http://v8.1c.ru/8.3/xcf/enums" xmlns:xpr="http://v8.1c.ru/8.3/xcf/predef" xmlns:xr="http://v8.1c.ru/8.3/xcf/readable" xmlns:xs="http://www.w3.org/2001/XMLSchema" xmlns:xsi="http://www.w3.org/2001/XMLSchema-instance" version="2.18">
	<FunctionalOption uuid="93971fd1-fb56-4f5f-9074-e585d14d5693">
		<Properties>
			<Name>ИспользоватьКадровыйРезерв</Name>
			<Synonym>
				<v8:item>
					<v8:lang>ru</v8:lang>
					<v8:content>Использовать кадровый резерв</v8:content>
				</v8:item>
			</Synonym>
			<Comment/>
			<Location>InformationRegister.НастройкиКадровогоРезерва.Resource.ИспользоватьКадровыйРезерв</Location>
			<PrivilegedGetMode>true</PrivilegedGetMode>
			<Content>
				<xr:Object>Catalog.КадровыйРезерв</xr:Object>
				<xr:Object>Document.ИсключениеИзКадровогоРезерва</xr:Object>
				<xr:Object>Document.ВключениеВКадровыйРезерв</xr:Object>
				<xr:Object>DocumentJournal.ДокументыКадровогоРезерва</xr:Object>
				<xr:Object>Subsystem.ОбучениеИРазвитие.Subsystem.КадровыйРезерв</xr:Object>
				<xr:Object>Enum.ДействияСКадровымиРезервистами</xr:Object>
				<xr:Object>Document.КадровыйПеревод.TabularSection.КадровыйРезерв</xr:Object>
				<xr:Object>Document.КадровыйПереводСписком.TabularSection.КадровыйРезерв</xr:Object>
				<xr:Object>Document.РезультатыАттестацииСотрудников.TabularSection.РезультатыАттестации.Attribute.ПозицияРезерва</xr:Object>
				<xr:Object>Document.Увольнение.TabularSection.КадровыйРезерв</xr:Object>
				<xr:Object>Document.УвольнениеСписком.TabularSection.КадровыйРезерв</xr:Object>
				<xr:Object>Subsystem.ОбучениеИРазвитие</xr:Object>
			</Content>
		</Properties>
	</FunctionalOption>
</MetaDataObject>